Workbook

Sheet Scraped data 
A1: Company Name | B1: Date | C1: Instruments | D1: Size | E1: Current Ratings | F1: Outlook | G1: Rating Rationale PDF | H1: Source URL
A2: Air Perfection | B2: July 18, 2025 | C2: Long Term Bank Facility | D2: Rs. 9.00 Cr. | E2: IVR C (INC)(Downgraded) | F2: Negative | G2: https://infomericstorage.blob.core.windows.net/uploads/pr_Air_Perfection_18july25_138dc0658d.pdf | H2: https://www.infomerics.com/pressrelease/air-perfection
A3: Air Perfection | B3: July 18, 2025 | C3: Short Term Facility | D3: Rs. 10.00 Cr. | E3: IVR A4 (INC)(Reaffirmed) | F3: Nil | G3: https://infomericstorage.blob.core.windows.net/uploads/pr_Air_Perfection_18july25_138dc0658d.pdf | H3: https://www.infomerics.com/pressrelease/air-perfection
A4: Uniproducts India Limited | B4: January 25, 2021 | C4: Long Term Bank Facilities | D4: Rs. 180.00 Cr. | E4: IVR BB (Revised and withdrawn) | F4: Stable | G4: https://infomericstorage.blob.core.windows.net/uploads/pr_uniproducts_india_ltd_jan25_2021_f888300be0.pdf | H4: https://www.infomerics.com/pressrelease/uniproducts-india-limited
A5: Uniproducts India Limited | B5: January 25, 2021 | C5: Short Term Bank Facilities | D5: Rs. 20.00 Cr. | E5: IVR A4 (Revised and withdrawn) | F5: Nil | G5: https://infomericstorage.blob.core.windows.net/uploads/pr_uniproducts_india_ltd_jan25_2021_f888300be0.pdf | H5: https://www.infomerics.com/pressrelease/uniproducts-india-limited
A6: Mitsumi Housing Private Limited | B6: October 28, 2021 | C6: Long Term Fund Based Facility - Cash Credit (Proposed) | D6: NIL | E6: Withdrawn | F6: Nil | G6: https://infomericstorage.blob.core.windows.net/uploads/pr_mitsumi_housing_oct28_2021_bc1db02e68.pdf | H6: https://www.infomerics.com/pressrelease/mitsumi-housing-private-limited
A7: Mitsumi Housing Private Limited | B7: October 28, 2021 | C7: Short Term Non-Fund Based Facility - Bank Guarantee (Proposed) | D7: NIL | E7: Withdrawn | F7: Nil | G7: https://infomericstorage.blob.core.windows.net/uploads/pr_mitsumi_housing_oct28_2021_bc1db02e68.pdf | H7: https://www.infomerics.com/pressrelease/mitsumi-housing-private-limited
A8: Grand Canyon SEZ Private Limited | B8: October 14, 2025 | C8: Long Term Bank Facilities - LRD | D8: Rs. 283.03 Cr. | E8: IVR BB (INC)(Downgraded) | F8: Negative | G8: https://infomericstorage.blob.core.windows.net/uploads/pr_grand_canyonsez_14oct25_d2c647af6c.pdf | H8: https://www.infomerics.com/pressrelease/grand-canyon-sez-private-limited
A9: Nayati Medical Private Limited (Formerly known as Nayati Pharma Private Limited) | B9: February 17, 2025 | C9: Long Term Bank Facilities | D9: Rs. 10.00 Cr. | E9: IVR C- (INC)(Downgraded) | F9: Negative | G9: https://infomericstorage.blob.core.windows.net/uploads/pr_nayati_medical_17feb25_0f07ecf4d0.pdf | H9: https://www.infomerics.com/pressrelease/nayati-medical-private-limited-(formerly-known-as-nayati-pharma-private-limited)
A10: Suraksha Asset Reconstruction Private Limited (SARPL) | B10: October 12, 2019 | C10: Commercial Paper | D10: Rs. 600.00 Cr. | E10: IVR A1+ (CE) (Withdrawn) | F10: Nil | G10: # | H10: https://www.infomerics.com/pressrelease/suraksha-asset-reconstruction-private-limited-(sarpl)
A11: Unimed Technologies Limited | B11: October 12, 2019 | C11: Commercial Paper | D11: Rs. 500.00 Cr. | E11: IVR A1+ (CE) (Withdrawn) | F11: Nil | G11: https://infomericstorage.blob.core.windows.net/uploads/PR_UTL_Withdrawal_12_10_2019_a52bef172c.pdf | H11: https://www.infomerics.com/pressrelease/unimed-technologies-limited
A12: MJ Pharmaceuticals Private Limited | B12: October 12, 2019 | C12: Commercial Paper | D12: Rs. 750.00 Cr. | E12: IVR A1+ (CE) (Withdrawn) | F12: Nil | G12: https://infomericstorage.blob.core.windows.net/uploads/PR_MJ_Pharmaceuticals_12_10_2019_976b1b62f0.pdf | H12: https://www.infomerics.com/pressrelease/mj-pharmaceuticals-private-limited
... A52: Achiievers Finance India Limited | B52: October 6, 2025 | C52: Proposed Non-Convertible Debentures | D52: Rs. 35.37 Cr. (Increased from Rs. 9.45 Cr.) | E52: IVR BBB- (Upgraded) | F52: Stable | G52: https://infomericstorage.blob.core.windows.net/uploads/pr_achiievers_finance_6oct25_daf21f7389.pdf | H52: https://www.infomerics.com/pressrelease/achiievers-finance-india-limited
A53: Achiievers Finance India Limited | B53: October 6, 2025 | C53: Non-Convertible Debentures | D53: 0 | E53: Withdrawn | F53: Nil | G53: https://infomericstorage.blob.core.windows.net/uploads/pr_achiievers_finance_6oct25_daf21f7389.pdf | H53: https://www.infomerics.com/pressrelease/achiievers-finance-india-limited
A54: Simplex Infrastructures Limited | B54: September 24, 2025 | C54: Long Term Bank Facilities | D54: Rs. 2600.00 Cr. | E54: IVR D (INC)(Reaffirmed) | F54: Nil | G54: https://infomericstorage.blob.core.windows.net/uploads/pr_simplex_infra_24sep25_6ac9ced126.pdf | H54: https://www.infomerics.com/pressrelease/simplex-infrastructures-limited
A55: Simplex Infrastructures Limited | B55: September 24, 2025 | C55: Short Term Bank Facilities | D55: Rs. 75.00 Cr. | E55: IVR D (INC)(Reaffirmed) | F55: Nil | G55: https://infomericstorage.blob.core.windows.net/uploads/pr_simplex_infra_24sep25_6ac9ced126.pdf | H55: https://www.infomerics.com/pressrelease/simplex-infrastructures-limited
A56: Nidhi Textiles | B56: December 11, 2018 | C56: Long Term Fund Based Limits | D56: Rs. 9.00 cr. | E56: IVR BB- (Reaffirmed and Withdrawn) | F56: Stable | G56: https://infomericstorage.blob.core.windows.net/uploads/Press_Release_Nidhi_withdrawal_077eac4a81.pdf | H56: https://www.infomerics.com/pressrelease/nidhi-textiles
A57: Nidhi Textiles | B57: December 11, 2018 | C57: Working Capital Demand Loan | D57: Rs.2.50 Cr. | E57: IVR BB- (Reaffirmed and Withdrawn) | F57: Stable | G57: https://infomericstorage.blob.core.windows.net/uploads/Press_Release_Nidhi_withdrawal_077eac4a81.pdf | H57: https://www.infomerics.com/pressrelease/nidhi-textiles
A58: Gemini Fashion | B58: December 11, 2018 | C58: Long Term Fund Based Limits | D58: Rs. 6.00 cr. | E58: IVR BB- (Reaffirmed and Withdrawn) | F58: Stable | G58: https://infomericstorage.blob.core.windows.net/uploads/Press_Release_Gemini_Withdrawal_f9d45f3bcb.pdf | H58: https://www.infomerics.com/pressrelease/gemini-fashion
A59: Gemini Fashion | B59: December 11, 2018 | C59: Working Capital Demand Loan | D59: Rs.2.50 Cr. | E59: IVR BB- (Reaffirmed and Withdrawn) | F59: Stable | G59: https://infomericstorage.blob.core.windows.net/uploads/Press_Release_Gemini_Withdrawal_f9d45f3bcb.pdf | H59: https://www.infomerics.com/pressrelease/gemini-fashion
A60: Shriniwas Spintex Industries Private Limited | B60: December 29, 2025 | C60: Long Term Fund Based Bank Facilities | D60: Rs. 33.03 Cr. | E60: IVR BB (INC)(Downgraded) | F60: Negative | G60: https://infomericstorage.blob.core.windows.net/uploads/pr_SSIPL_29dec25_2e2982e02d.pdf | H60: https://www.infomerics.com/pressrelease/shriniwas-spintex-industries-private-limited
A61: Shriniwas Spintex Industries Private Limited | B61: December 29, 2025 | C61: Short Term Non-Fund Based Bank Facilities | D61: Rs. 1.90 Cr. | E61: IVR A4 (ISSUER NOT COOPERATING) | F61: Nil | G61: https://infomericstorage.blob.core.windows.net/uploads/pr_SSIPL_29dec25_2e2982e02d.pdf | H61: https://www.infomerics.com/pressrelease/shriniwas-spintex-industries-private-limited
A62: Velan Kraft House Private Limited | B62: July 17, 2025 | C62: Long Term Bank Facilities | D62: Rs. 43.00 Cr. | E62: IVR D (INC)(Reaffirmed) | F62: Nil | G62: https://infomericstorage.blob.core.windows.net/uploads/pr_velankraft_17july25_7587ffe110.pdf | H62: https://www.infomerics.com/pressrelease/velan-kraft-house-private-limited
A63: Anvil Energy Private Limited (erstwhile Anvil Cables Private Limited) | B63: January 27, 2026 | C63: Long Term Bank Facilities | D63: Rs. 147.30 Cr. (enhanced from Rs. 90.47 Cr. and includes proposed facility of Rs. 16.00 Cr.) | E63: IVR BBB+ (Reaffirmed) | F63: Stable | G63: https://infomericstorage.blob.core.windows.net/uploads/pr_Anvil_Energy_27jan26_718f2983a4.pdf | H63: https://www.infomerics.com/pressrelease/anvil-energy-private-limited-erstwhile-anvil-cables-private-limited
A64: Anvil Energy Private Limited (erstwhile Anvil Cables Private Limited) | B64: January 27, 2026 | C64: Short Term Bank Facilities | D64: Rs. 215.50 Cr. (enhanced from Rs. 109.33 Cr. and includes proposed facility of Rs. 31.32 Cr.) | E64: IVR A2 (Reaffirmed) | F64: Nil | G64: https://infomericstorage.blob.core.windows.net/uploads/pr_Anvil_Energy_27jan26_718f2983a4.pdf | H64: https://www.infomerics.com/pressrelease/anvil-energy-private-limited-erstwhile-anvil-cables-private-limited
A65: YSR Spinning and Weaving Mills Private Limited | B65: March 24, 2021 | C65: Long Term Bank Facilities | D65: Rs. 20.20 Cr. | E65: IVR BB (Withdrawn) | F65: Stable | G65: https://infomericstorage.blob.core.windows.net/uploads/pr_ysr_spinning_weaving_mar24_2021_06df102372.pdf | H65: https://www.infomerics.com/pressrelease/ysr-spinning-and-weaving-mills-private-limited
... A74: Usha Financial Services Limited | B74: December 5, 2025 | C74: Proposed Long Term Fund Based Bank Facilities - Term Loan | D74: Rs. 66.37 Cr. | E74: IVR BBB- (Downgraded) | F74: Stable | G74: https://infomericstorage.blob.core.windows.net/uploads/PR_Usha_Financial_Services05_Dec25_768202b3d1.pdf | H74: https://www.infomerics.com/pressrelease/usha-financial-services-limited
A75: Usha Financial Services Limited | B75: December 5, 2025 | C75: Long Term Fund Based Bank Facilities - Term Loan | D75: 0 | E75: Withdrawn | F75: Nil | G75: https://infomericstorage.blob.core.windows.net/uploads/PR_Usha_Financial_Services05_Dec25_768202b3d1.pdf | H75: https://www.infomerics.com/pressrelease/usha-financial-services-limited
A76: Rean Watertech Private Limited | B76: July 31, 2025 | C76: Long Term Facilities | D76: Rs. 46.15 Cr. | E76: IVR BBB (Upgraded) (Withdrawn) | F76: Stable | G76: https://infomericstorage.blob.core.windows.net/uploads/Pr_Rean_Watertech_31july25_fc7e889103.pdf | H76: https://www.infomerics.com/pressrelease/rean-watertech-private-limited
A77: Rean Watertech Private Limited | B77: July 31, 2025 | C77: Long Term / Short Term Facilities | D77: Rs. 5.85 Cr. | E77: IVR BBB/ IVR A3+ (Upgraded)(Withdrawn) | F77: Stable/- | G77: https://infomericstorage.blob.core.windows.net/uploads/Pr_Rean_Watertech_31july25_fc7e889103.pdf | H77: https://www.infomerics.com/pressrelease/rean-watertech-private-limited
A78: Aavanti Renewable Energy Private Limited | B78: October 9, 2024 | C78: Long Term Bank Facilities | D78: Rs. 0.00 Cr. | E78: Withdrawn | F78: Nil | G78: https://infomericstorage.blob.core.windows.net/uploads/Pr_Aavanti_Renewable_Energy_9oct24_262d912977.pdf | H78: https://www.infomerics.com/pressrelease/aavanti-renewable-energy-private-limited
A79: Kanak Instalments Limited | B79: August 8, 2025 | C79: Long Term Fund Based Limits (Proposed) | D79: Rs. 5.00 Cr. | E79: IVR B- (INC)(Reaffirmed) | F79: Negative | G79: https://infomericstorage.blob.core.windows.net/uploads/pr_kanak_instalments_8aug25_aa9e787a12.pdf | H79: https://www.infomerics.com/pressrelease/kanak-instalments-limited
A80: MEP Longjian VTR Private Limited | B80: October 29, 2025 | C80: Long Term Bank Facilities - Proposed | D80: Rs. 646.93 Cr. | E80: IVR C- (INC)(Downgraded) | F80: Negative | G80: https://infomericstorage.blob.core.windows.net/uploads/pr_MEP_Longjian_VTR_29oct25_a9cf596c84.pdf | H80: https://www.infomerics.com/pressrelease/mep-longjian-vtr-private-limited
A81: AP Securitas Private Limited | B81: November 9, 2022 | C81: Long Term Bank Facilities - Cash Credit | D81: Rs. 34.00 Cr. | E81: IVR BBB (Reaffirmed and withdrawn) | F81: Stable | G81: https://infomericstorage.blob.core.windows.net/uploads/pr_AP_Securitas_9nov22_1bd69a386e.pdf | H81: https://www.infomerics.com/pressrelease/ap-securitas-private-limited
A82: AP Securitas Private Limited | B82: November 9, 2022 | C82: Short Term Bank Facilities - Sales Invoice Discounting | D82: Rs. 15.00 Cr. | E82: IVR A3+ (Reaffirmed and withdrawn) | F82: Nil | G82: https://infomericstorage.blob.core.windows.net/uploads/pr_AP_Securitas_9nov22_1bd69a386e.pdf | H82: https://www.infomerics.com/pressrelease/ap-securitas-private-limited
A83: AP Securitas Private Limited | B83: November 9, 2022 | C83: Short Term Bank Facilities - Bank Guarantee | D83: Rs. 15.00 Cr. | E83: IVR A3+ (Reaffirmed and withdrawn) | F83: Nil | G83: https://infomericstorage.blob.core.windows.net/uploads/pr_AP_Securitas_9nov22_1bd69a386e.pdf | H83: https://www.infomerics.com/pressrelease/ap-securitas-private-limited
A84: JPM Exports Private Limited | B84: June 19, 2025 | C84: Long Term Bank Facilities | D84: Rs. 50.00 Cr. | E84: IVR D (INC)(Reaffirmed) | F84: Nil | G84: https://infomericstorage.blob.core.windows.net/uploads/pr_JPM_Exports_19june25_cdd6900534.pdf | H84: https://www.infomerics.com/pressrelease/jpm-exports-private-limited
A85: Mahadev Yarns Private Limited | B85: December 29, 2021 | C85: Long Term Fund Based Facilities - Term Loan | D85: Rs. 4.14 Cr. | E85: IVR B (INC)(Reaffirmed and Withdrawn) | F85: Nil | G85: https://infomericstorage.blob.core.windows.net/uploads/pr_Mahadev_Yarns_29dec21_53e5656ffb.pdf | H85: https://www.infomerics.com/pressrelease/mahadev-yarns-private-limited
A86: Mahadev Yarns Private Limited | B86: December 29, 2021 | C86: Long Term Bank Facilities - Cash Credit | D86: Rs. 11.36 Cr. (including proposed limit of Rs. 0.36 crore) | E86: IVR B (INC)(Reaffirmed and Withdrawn) | F86: Nil | G86: https://infomericstorage.blob.core.windows.net/uploads/pr_Mahadev_Yarns_29dec21_53e5656ffb.pdf | H86: https://www.infomerics.com/pressrelease/mahadev-yarns-private-limited
A87: Mahadev Yarns Private Limited | B87: December 29, 2021 | C87: Short Term Bank Facilities - Bank Guarantee | D87: Rs. 0.50 Cr. | E87: IVR A4 (INC)(Reaffirmed and Withdrawn) | F87: Nil | G87: https://infomericstorage.blob.core.windows.net/uploads/pr_Mahadev_Yarns_29dec21_53e5656ffb.pdf | H87: https://www.infomerics.com/pressrelease/mahadev-yarns-private-limited
... A308: Aavri Overseas Private Limited (erstwhile Logan Minerals Private Limited) | B308: October 6, 2025 | C308: Long Term / Short Term Bank Facilities | D308: Rs. 20.00 Cr. | E308: IVR BBB-/IVR A3; (INC)(Downgraded) | F308: Negative/- | G308: https://infomericstorage.blob.core.windows.net/uploads/pr_aavri_overseas_6oct25_4b6a7ece76.pdf | H308: https://www.infomerics.com/pressrelease/aavri-overseas-private-limited-erstwhile-logan-minerals-private-limited
A309: Jupiter Hospital Projects Private Limited | C309: Long Term Bank Facilities | D309: 0.00 (Reduced from Rs. 170.00 Crore) | E309: Withdrawn | F309: Nil | G309: https://infomericstorage.blob.core.windows.net/uploads/pr_jupiter_hospital_20nov25_60c407a92e.pdf | H309: https://www.infomerics.com/pressrelease/jupiter-hospital-projects-private-limited
A310: Jupiter Hospital Projects Private Limited | C310: Short Term Bank Facilities | D310: 0.00 (Reduced from Rs 10.00 Crore) | E310: Withdrawn | F310: Nil | G310: https://infomericstorage.blob.core.windows.net/uploads/pr_jupiter_hospital_20nov25_60c407a92e.pdf | H310: https://www.infomerics.com/pressrelease/jupiter-hospital-projects-private-limited
A311: Vishesh Diagnostics Private Limited | B311: January 21, 2021 | C311: Long Term Fund Based Facility - Term Loan | D311: - | E311: Withdrawn | F311: Nil | G311: https://infomericstorage.blob.core.windows.net/uploads/pr_vishesh_diagnostics_jan21_2021_4389904270.pdf | H311: https://www.infomerics.com/pressrelease/vishesh-diagnostics-private-limited
A312: Vishesh Diagnostics Private Limited | B312: January 21, 2021 | C312: (Proposed) Long Term Fund Based Facility - Term Loan | D312: - | E312: Withdrawn | F312: Nil | G312: https://infomericstorage.blob.core.windows.net/uploads/pr_vishesh_diagnostics_jan21_2021_4389904270.pdf | H312: https://www.infomerics.com/pressrelease/vishesh-diagnostics-private-limited
A313: Vishesh Diagnostics Private Limited | B313: January 21, 2021 | C313: Short Term Facility - Fund Based - Overdraft | D313: - | E313: Withdrawn | F313: Nil | G313: https://infomericstorage.blob.core.windows.net/uploads/pr_vishesh_diagnostics_jan21_2021_4389904270.pdf | H313: https://www.infomerics.com/pressrelease/vishesh-diagnostics-private-limited
A314: Vishesh Diagnostics Private Limited | B314: January 21, 2021 | C314: (Proposed) Short Term Facility - Fund Based - Overdraft | D314: - | E314: Withdrawn | F314: Nil | G314: https://infomericstorage.blob.core.windows.net/uploads/pr_vishesh_diagnostics_jan21_2021_4389904270.pdf | H314: https://www.infomerics.com/pressrelease/vishesh-diagnostics-private-limited
A315: Regaal Resources Private Limited | B315: December 12, 2022 | C315: Long Term Bank Facilities | D315: - | E315: Withdrawn | F315: Nil | G315: https://infomericstorage.blob.core.windows.net/uploads/pr_Regaal_Resources_12dec22_a6d0cba6b1.pdf | H315: https://www.infomerics.com/pressrelease/regaal-resources-private-limited
A316: Spanv Medisearch Lifesciences Private Limited | B316: January 5, 2022 | C316: Proposed Long Term Bank Facilities - Term Loan | D316: Rs. 190.00 Cr. | E316: Provisional IVR A (CE)(Withdrawn) | F316: Stable | G316: https://infomericstorage.blob.core.windows.net/uploads/pr_spanv_medisearch_05jan22_e03d7dc4f0.pdf | H316: https://www.infomerics.com/pressrelease/spanv-medisearch-lifesciences-private-limited
A317: Spanv Medisearch Lifesciences Private Limited | B317: January 5, 2022 | C317: Proposed Long Term Bank Facilities - Cash Credit | D317: Rs. 15.00 Cr. | E317: Provisional IVR A (CE)(Withdrawn) | F317: Stable | G317: https://infomericstorage.blob.core.windows.net/uploads/pr_spanv_medisearch_05jan22_e03d7dc4f0.pdf | H317: https://www.infomerics.com/pressrelease/spanv-medisearch-lifesciences-private-limited
A318: Amrit Papers Private Limited (Erstwhile Amrit Agencies Indore Private Limited) | B318: December 10, 2025 | C318: Long Term Bank Facilities | D318: Rs. 169.06 Cr. | E318: IVR BB+ (INC)(Downgraded) | F318: Negative | G318: https://infomericstorage.blob.core.windows.net/uploads/pr_amrit_papers_10dec25_9a5c8ceabb.pdf | H318: https://www.infomerics.com/pressrelease/amrit-papers-private-limited-erstwhile-amrit-agencies-indore-private-limited
A319: Amrit Papers Private Limited (Erstwhile Amrit Agencies Indore Private Limited) | B319: December 10, 2025 | C319: Short Term Bank Facilities | D319: Rs. 5.00 Cr. | E319: IVR A4+ (INC)(Downgraded) | F319: Nil | G319: https://infomericstorage.blob.core.windows.net/uploads/pr_amrit_papers_10dec25_9a5c8ceabb.pdf | H319: https://www.infomerics.com/pressrelease/amrit-papers-private-limited-erstwhile-amrit-agencies-indore-private-limited
A320: Premier Marine Foods | B320: March 26, 2025 | C320: Long Term Bank Facilities | D320: Rs. 12.67 Cr. | E320: IVR D (INC) (Reaffirmed) | F320: Nil | G320: https://infomericstorage.blob.core.windows.net/uploads/Pr_Premier_Marine_26mar25_e01d6cfef0.pdf | H320: https://www.infomerics.com/pressrelease/premier-marine-foods
A321: Premier Marine Foods | B321: March 26, 2025 | C321: Short Term Bank Facilities | D321: Rs. 56.00 Cr. | E321: IVR D (INC) (Reaffirmed) | F321: Nil | G321: https://infomericstorage.blob.core.windows.net/uploads/Pr_Premier_Marine_26mar25_e01d6cfef0.pdf | H321: https://www.infomerics.com/pressrelease/premier-marine-foods
A322: Kids Impex | B322: August 26, 2025 | C322: Long Term Bank Facilities | D322: Rs. 5.76 Cr. | E322: IVR C+ (INC)(Downgraded) | F322: Negative | G322: https://infomericstorage.blob.core.windows.net/uploads/pr_kids_impex_26aug2025_eea76c0895.pdf | H322: https://www.infomerics.com/pressrelease/kids-impex
... A554: Raudra Technocrats Private Limited | B554: July 7, 2025 | C554: Short Term Non fund based limits | D554: Rs. 5.00 Cr. | E554: IVR A4 (INC)(Reaffirmed) | F554: Nil | G554: https://infomericstorage.blob.core.windows.net/uploads/Pr_Raudra_Technocrat_7july25_e541edff78.pdf | H554: https://www.infomerics.com/pressrelease/raudra-technocrats-private-limited
A555: ARCL Organics Limited | B555: November 25, 2025 | C555: Long Term Bank Facilities | D555: 0 | E555: Withdrawn | F555: Nil | G555: https://infomericstorage.blob.core.windows.net/uploads/pr_ARCL_Organics_25nov25_d24221fc63.pdf | H555: https://www.infomerics.com/pressrelease/arcl-organics-limited
A556: ARCL Organics Limited | B556: November 25, 2025 | C556: Short Term Bank Facilities | D556: 0 | E556: Withdrawn | F556: Nil | G556: https://infomericstorage.blob.core.windows.net/uploads/pr_ARCL_Organics_25nov25_d24221fc63.pdf | H556: https://www.infomerics.com/pressrelease/arcl-organics-limited
A557: Maya Construction Company Private Limited | B557: May 23, 2025 | C557: Long Term Bank Facilities | D557: Rs. 5.00 Cr. | E557: IVR C+ (INC)(Downgraded) | F557: Negative | G557: https://infomericstorage.blob.core.windows.net/uploads/pr_maya_construction_23may25_18f885ae6e.pdf | H557: https://www.infomerics.com/pressrelease/maya-construction-company-private-limited
A558: Maya Construction Company Private Limited | B558: May 23, 2025 | C558: Short Term Bank Facilities | D558: Rs. 5.00 Cr. | E558: IVR A4 (INC)(Reaffirmed) | F558: Nil | G558: https://infomericstorage.blob.core.windows.net/uploads/pr_maya_construction_23may25_18f885ae6e.pdf | H558: https://www.infomerics.com/pressrelease/maya-construction-company-private-limited
A559: Devi Iron & Power Private Limited | B559: December 23, 2025 | C559: Long Term Bank Facilities | D559: Rs. 172.48 Cr. (enhanced from Rs. 153.61 Cr.) | E559: IVR A (Upgraded) | F559: Stable | G559: https://infomericstorage.blob.core.windows.net/uploads/PR_Devi_Iron_and_Power23_Dec25_64c07f1476.pdf | H559: https://www.infomerics.com/pressrelease/devi-iron-power-private-limited
A560: Agrawal Channel Mills Private Limited | B560: September 23, 2025 | C560: Long Term Bank Facilities | D560: Rs. 55.32 Cr. (enhanced from Rs. 44.90 Crore) | E560: IVR BBB+ (Upgraded) | F560: Stable | G560: https://infomericstorage.blob.core.windows.net/uploads/pr_agrawal_channelmills_23sep25_2aa0c34f8c.pdf | H560: https://www.infomerics.com/pressrelease/agrawal-channel-mills-private-limited
A561: Akriti Sales Corporation | B561: August 5, 2021 | C561: Long Term Fund Based Facility - Cash Credit | D561: Rs 31.75 Cr | E561: IVR BB+ (Reaffirmed & Withdrawn) | F561: Stable | G561: https://infomericstorage.blob.core.windows.net/uploads/pr_Akriti_Sales_Corporation_5_aug_21_9cdb171559.pdf | H561: https://www.infomerics.com/pressrelease/akriti-sales-corporation-
A562: Akriti Sales Corporation | B562: August 5, 2021 | C562: Long Term Fund Based Facility- Channel Finance | D562: Rs 6.50 Cr | E562: IVR BB+ (Reaffirmed &Withdrawn) | F562: Stable | G562: https://infomericstorage.blob.core.windows.net/uploads/pr_Akriti_Sales_Corporation_5_aug_21_9cdb171559.pdf | H562: https://www.infomerics.com/pressrelease/akriti-sales-corporation-
A563: Akriti Sales Corporation | B563: August 5, 2021 | C563: Short Term Non Fund Based Facility- Bank Guarantee | D563: Rs 1.00 Cr | E563: IVR A4+ (Reaffirmed & Withdrawn) | F563: Nil | G563: https://infomericstorage.blob.core.windows.net/uploads/pr_Akriti_Sales_Corporation_5_aug_21_9cdb171559.pdf | H563: https://www.infomerics.com/pressrelease/akriti-sales-corporation-
A564: Akriti Sales Corporation | B564: August 5, 2021 | C564: Long Term Fund Based Facility - Cash Credit | D564: Rs 31.75 Cr | E564: IVR BB+ (Reaffirmed & Withdrawn) | F564: Stable | G564: https://infomericstorage.blob.core.windows.net/uploads/pr_Akriti_Sales_Corporation_5_aug_21_9cdb171559.pdf | H564: https://www.infomerics.com/pressrelease/akriti-sales-corporation-
A565: Akriti Sales Corporation | B565: August 5, 2021 | C565: Long Term Fund Based Facility- Channel Finance | D565: Rs 6.50 Cr | E565: IVR BB+ (Reaffirmed &Withdrawn) | F565: Stable | G565: https://infomericstorage.blob.core.windows.net/uploads/pr_Akriti_Sales_Corporation_5_aug_21_9cdb171559.pdf | H565: https://www.infomerics.com/pressrelease/akriti-sales-corporation-
A566: Akriti Sales Corporation | B566: August 5, 2021 | C566: Short Term Non Fund Based Facility- Bank Guarantee | D566: Rs 1.00 Cr | E566: IVR A4+ (Reaffirmed & Withdrawn) | F566: Nil | G566: https://infomericstorage.blob.core.windows.net/uploads/pr_Akriti_Sales_Corporation_5_aug_21_9cdb171559.pdf | H566: https://www.infomerics.com/pressrelease/akriti-sales-corporation-
A567: Unique Construction | B567: September 8, 2025 | C567: Long Term Bank Facilities | D567: Rs. 18.00 Cr. | E567: IVR BBB- (INC)(Downgraded) | F567: Negative | G567: https://infomericstorage.blob.core.windows.net/uploads/pr_unique_construction_8sep25_a0f870f539.pdf | H567: https://www.infomerics.com/pressrelease/unique-construction
A568: Unique Construction | B568: September 8, 2025 | C568: Short Term Bank Facilities | D568: Rs. 182.00 Cr. | E568: IVR A3 (INC)(Downgraded) | F568: Nil | G568: https://infomericstorage.blob.core.windows.net/uploads/pr_unique_construction_8sep25_a0f870f539.pdf | H568: https://www.infomerics.com/pressrelease/unique-construction
... A834: Shree Banke Bihari Ispat Private Limited | B834: January 20, 2026 | C834: Long Term Bank Facilities | D834: Rs. 27.76 Cr. (Reduced from Rs. 29.88 Crore) | E834: IVR BBB (Reaffirmed) | F834: Stable | G834: https://infomericstorage.blob.core.windows.net/uploads/pr_SBBIPL_20jan26_8e950e87ba.pdf | H834: https://www.infomerics.com/pressrelease/shree-banke-bihari-ispat-private-limited
A835: Srivatsav Urban Estates & Developers Private Limited (Erstwhile M G M Castings Private Limited) | B835: June 10, 2024 | C835: Long Term Bank Facilities | D835: -- | E835: =-- (Withdrawn) -> #NAME? | F835: Nil | G835: https://infomericstorage.blob.core.windows.net/uploads/PR_Srivatsav_UED_10june24_7b369476fa.pdf | H835: https://www.infomerics.com/pressrelease/srivatsav-urban-estates--developers-private-limited-erstwhile-m-g-m-castings-private-limited
A836: Marda Industries Private Limited | B836: July 7, 2025 | C836: Long Term Bank Facilities - Cash Credit | D836: Rs. 1.35 Cr. | E836: IVR C+ (INC)(Downgraded) | F836: Negative | G836: https://infomericstorage.blob.core.windows.net/uploads/pr_marda_industries_7july25_ac6f28c7a8.pdf | H836: https://www.infomerics.com/pressrelease/marda-industries-private-limited
A837: Marda Industries Private Limited | B837: July 7, 2025 | C837: Long Term Bank Facilities - Term Loan | D837: Rs. 11.50 Cr. | E837: IVR C+ (INC)(Reaffirmed) | F837: Negative | G837: https://infomericstorage.blob.core.windows.net/uploads/pr_marda_industries_7july25_ac6f28c7a8.pdf | H837: https://www.infomerics.com/pressrelease/marda-industries-private-limited
A838: SCC Builders Private Limited | B838: July 22, 2025 | C838: Long Term Bank Facilities | D838: Rs. 148.10 Cr. | E838: IVR BB- (INC)(Downgraded) | F838: Negative | G838: https://infomericstorage.blob.core.windows.net/uploads/pr_scc_builders_22july25_e52e6a8986.pdf | H838: https://www.infomerics.com/pressrelease/scc-builders-private-limited
A839: Kalpataruvu Spinning Mills Private Limited | B839: December 16, 2024 | C839: Long Term Bank Facilities | D839: Rs. 49.13 Cr. | E839: IVR D (INC)(Downgraded) | F839: Nil | G839: https://infomericstorage.blob.core.windows.net/uploads/pr_Kalpataruvu_Spinning_16dec24_7ed0e20e60.pdf | H839: https://www.infomerics.com/pressrelease/kalpataruvu-spinning-mills-private-limited
A840: Ramnik Power and Alloys Private Limited | B840: November 13, 2025 | C840: Long Term Fund Based Facilities - Cash Credit | D840: Rs. 37.00 Cr. | E840: IVR BBB- (Upgraded and Withdrawn) | F840: Stable | G840: https://infomericstorage.blob.core.windows.net/uploads/pr_ramnik_power_13nov25_ca768a8ea7.pdf | H840: https://www.infomerics.com/pressrelease/ramnik-power-and-alloys-private-limited
A841: Ramnik Power and Alloys Private Limited | B841: November 13, 2025 | C841: Long Term Fund Based Facilities - Term Loan | D841: Rs. 102.18 Cr. (Reduced from Rs. 108.09 Crore) | E841: IVR BBB- (Upgraded and Withdrawn) | F841: Stable | G841: https://infomericstorage.blob.core.windows.net/uploads/pr_ramnik_power_13nov25_ca768a8ea7.pdf | H841: https://www.infomerics.com/pressrelease/ramnik-power-and-alloys-private-limited
A842: Ramnik Power and Alloys Private Limited | B842: November 13, 2025 | C842: Long Term Fund Based Facilities - CECL Loan | D842: 0.00 (Previously rated amount Rs. 0.22 crore) | E842: Withdrawn | F842: Nil | G842: https://infomericstorage.blob.core.windows.net/uploads/pr_ramnik_power_13nov25_ca768a8ea7.pdf | H842: https://www.infomerics.com/pressrelease/ramnik-power-and-alloys-private-limited
A843: Ramnik Power and Alloys Private Limited | B843: November 13, 2025 | C843: Long Term Fund Based Facilities - Equipment Loan | D843: Rs. 0.07 Cr. (Reduced from Rs. 0.14 Crore) | E843: IVR BBB- (Upgraded and Withdrawn | F843: Stable | G843: https://infomericstorage.blob.core.windows.net/uploads/pr_ramnik_power_13nov25_ca768a8ea7.pdf | H843: https://www.infomerics.com/pressrelease/ramnik-power-and-alloys-private-limited
A844: Ramnik Power and Alloys Private Limited | B844: November 13, 2025 | C844: Short Term Non-Fund Based Facilities -Bank Guarantee | D844: Rs. 3.00 Cr. | E844: IVR A3 (Upgraded and Withdrawn) | F844: Nil | G844: https://infomericstorage.blob.core.windows.net/uploads/pr_ramnik_power_13nov25_ca768a8ea7.pdf | H844: https://www.infomerics.com/pressrelease/ramnik-power-and-alloys-private-limited
A845: Ramnik Power and Alloys Private Limited | B845: November 13, 2025 | C845: Short Term Non-Fund Based Facilities- Proposed Bank Guarantee | D845: 0.00 (Previously rated amount Rs. 24.55 crore) | E845: Withdrawn | F845: Nil | G845: https://infomericstorage.blob.core.windows.net/uploads/pr_ramnik_power_13nov25_ca768a8ea7.pdf | H845: https://www.infomerics.com/pressrelease/ramnik-power-and-alloys-private-limited
A846: RPP Infra Projects Limited | B846: October 29, 2025 | C846: Long Term Bank Facilities | D846: Rs. 63.00 Cr. | E846: IVR BBB+ (Upgraded and Withdrawn) | F846: Stable | G846: https://infomericstorage.blob.core.windows.net/uploads/PR_RPP_Inf29_Oct2025_e71489f3ff.pdf | H846: https://www.infomerics.com/pressrelease/rpp-infra-projects-limited
A847: RPP Infra Projects Limited | B847: October 29, 2025 | C847: Short Term Bank Facilities | D847: Rs. 288.52 Cr. | E847: IVR A2 (Upgraded & Withdrawn) | F847: Nil | G847: https://infomericstorage.blob.core.windows.net/uploads/PR_RPP_Inf29_Oct2025_e71489f3ff.pdf | H847: https://www.infomerics.com/pressrelease/rpp-infra-projects-limited
... A866: RBA Finance Private Limited | B866: March 7, 2024 | C866: Long Term Fund Based Facilities - Cash Credit | D866: Rs. 10.00 Cr. | E866: IVR BB+ (Upgraded, removed from INC category and simultaneously Withdrawn) | F866: Stable | G866: https://infomericstorage.blob.core.windows.net/uploads/PR_RBA_07032024_48499d4557.pdf | H866: https://www.infomerics.com/pressrelease/rba-finance-private-limited
A867: RBA Finance Private Limited | B867: March 7, 2024 | C867: Long Term Fund Based Limit - Term Loans | D867: Rs. 0.00 Cr. (reduced from Rs.1.33 crore). | E867: =-- Withdrawn -> #NAME? | F867: Nil | G867: https://infomericstorage.blob.core.windows.net/uploads/PR_RBA_07032024_48499d4557.pdf | H867: https://www.infomerics.com/pressrelease/rba-finance-private-limited
A868: RBA Finance Private Limited | B868: March 7, 2024 | C868: Proposed Long Term Fund Based Limit - Cash Credit | D868: Rs. 5.00 Cr. | E868: IVR BB+ (Upgraded, removed from INC category and simultaneously Withdrawn) | F868: Stable | G868: https://infomericstorage.blob.core.windows.net/uploads/PR_RBA_07032024_48499d4557.pdf | H868: https://www.infomerics.com/pressrelease/rba-finance-private-limited
A869: RBA Finance Private Limited | B869: March 7, 2024 | C869: Proposed Long Term Fund Based Limit - Cash Credit | D869: Rs. 13.67 Cr. | E869: IVR BB+ (Upgraded, removed from INC category and simultaneously Withdrawn) | F869: Stable | G869: https://infomericstorage.blob.core.windows.net/uploads/PR_RBA_07032024_48499d4557.pdf | H869: https://www.infomerics.com/pressrelease/rba-finance-private-limited
A870: Fabrimax Engineering Private Limited | B870: April 9, 2025 | C870: Long Term Facilities | D870: Rs. 22.24 Cr. (Reduced from Rs.24.00 crore) | E870: IVR BBB+ (Upgraded) | F870: Stable | G870: https://infomericstorage.blob.core.windows.net/uploads/Pr_Fabrimax_Engineering_9apr25_5b70fb618c.pdf | H870: https://www.infomerics.com/pressrelease/fabrimax-engineering-private-limited
A871: Fabrimax Engineering Private Limited | B871: April 9, 2025 | C871: Short term Facilities | D871: Rs. 17.50 Cr. | E871: IVR A2 (Upgraded) | F871: Nil | G871: https://infomericstorage.blob.core.windows.net/uploads/Pr_Fabrimax_Engineering_9apr25_5b70fb618c.pdf | H871: https://www.infomerics.com/pressrelease/fabrimax-engineering-private-limited
A872: Fabtech Engineering Private Limited | B872: April 9, 2025 | C872: Long Term Facilities | D872: Rs. 23.11 Cr. (Increased from Rs.19.50 crore) | E872: IVR BBB+ (Upgraded) | F872: Stable | G872: https://infomericstorage.blob.core.windows.net/uploads/Pr_Fabtech_Engineering_9apr25_069ab947f0.pdf | H872: https://www.infomerics.com/pressrelease/fabtech-engineering-private-limited
A873: Fabtech Engineering Private Limited | B873: April 9, 2025 | C873: Short term Facilities | D873: Rs. 43.25 Cr. (Increased from Rs.28.00 crore) | E873: IVR A2 (Upgraded) | F873: Nil | G873: https://infomericstorage.blob.core.windows.net/uploads/Pr_Fabtech_Engineering_9apr25_069ab947f0.pdf | H873: https://www.infomerics.com/pressrelease/fabtech-engineering-private-limited
A874: Shree Rupanadham Steel Private Limited | B874: January 20, 2026 | C874: Long Term Bank Facilities | D874: Rs. 105.32 Cr. (Reduced from Rs. 118.61 Crore) | E874: IVR BBB (Reaffirmed) | F874: Stable | G874: https://infomericstorage.blob.core.windows.net/uploads/PR_Shree_Rupanadham_Steel20_Jan26_fbf13dcfab.pdf | H874: https://www.infomerics.com/pressrelease/shree-rupanadham-steel-private-limited
A875: SKS Infra Projects Private Limited | B875: February 5, 2024 | C875: Short Term Bank Facilities | D875: Rs. 84.00 Cr. | E875: IVR A3 (Upgraded)(Withdrawn) | F875: Nil | G875: https://infomericstorage.blob.core.windows.net/uploads/pr_SKS_infraprojects_5feb24_c71bc24aa8.pdf | H875: https://www.infomerics.com/pressrelease/sks-infra-projects-private-limited
A876: SKS Infra Projects Private Limited | B876: February 5, 2024 | C876: Long Term Bank Facilities | D876: Rs. 21.00 Cr. | E876: IVR BBB- (Upgraded)(Withdrawn) | F876: Stable | G876: https://infomericstorage.blob.core.windows.net/uploads/pr_SKS_infraprojects_5feb24_c71bc24aa8.pdf | H876: https://www.infomerics.com/pressrelease/sks-infra-projects-private-limited
A877: Vishnu Chemicals Limited (VCL) | B877: May 3, 2023 | C877: Long term Bank Facilities - Term Loan | D877: Rs. 50.27 Cr. | E877: IVR BB+ (INC)(Withdrawn) | F877: Stable | G877: https://infomericstorage.blob.core.windows.net/uploads/pr_Vishnu_Chemicals_3may23_44c6babe31.pdf | H877: https://www.infomerics.com/pressrelease/vishnu-chemicals-limited-vcl
A878: Vishnu Chemicals Limited (VCL) | B878: May 3, 2023 | C878: Long term Bank Facilities - CECL/GECL 2.0 | D878: Rs. 35.59 Cr. | E878: IVR BB+ (INC)(Withdrawn) | F878: Stable | G878: https://infomericstorage.blob.core.windows.net/uploads/pr_Vishnu_Chemicals_3may23_44c6babe31.pdf | H878: https://www.infomerics.com/pressrelease/vishnu-chemicals-limited-vcl
A879: Vishnu Chemicals Limited (VCL) | B879: May 3, 2023 | C879: Long term Bank Facilities - Cash Credit | D879: Rs. 100.00 Cr. | E879: IVR BB+ (INC)(Withdrawn) | F879: Stable | G879: https://infomericstorage.blob.core.windows.net/uploads/pr_Vishnu_Chemicals_3may23_44c6babe31.pdf | H879: https://www.infomerics.com/pressrelease/vishnu-chemicals-limited-vcl
... A936: Bharat Realty Venture Private Limited | B936: May 28, 2025 | C936: Short term Bank Facilities - Bank Guarantee | D936: Rs. 7.50 Cr. | E936: IVR A3+ (Assigned) | F936: Nil | G936: https://infomericstorage.blob.core.windows.net/uploads/pr_bharat_realty_28may25_ff463e5537.pdf | H936: https://www.infomerics.com/pressrelease/bharat-realty-venture-private-limited
A937: Davanam Jewellers Private Limited | B937: September 13, 2024 | C937: Long Term Fund Based Facility | D937: =- (Previously Rs.81.00 crore) -> #NAME? | E937: Withdrawn | F937: Nil | G937: https://infomericstorage.blob.core.windows.net/uploads/pr_Davanam_Jewellers_13sep24_db259badcb.pdf | H937: https://www.infomerics.com/pressrelease/davanam-jewellers-private-limited
...

Sheet Server
A1: id | B1: documentId | C1: CompanyName | D1: PAN | E1: PANData | F1: isActive | G1: createdAt | H1: updatedAt | I1: publishedAt | J1: dummy | K1: slug | L1: final link | M1: Address | N1: Date | O1: SubTitle | P1: industry | Q1: id | R1: documentId | S1: IndustryTitle | T1: isActive | U1: createdAt | V1: updatedAt | W1: publishedAt | X1: meta
A2: 4481 | B2: h702i4gdaz9m5rdgzjt5h6ws | C2: Air Perfection | D2: =VLOOKUP(C2,'Scraped data '!A:A,1,0) -> Air Perfection | F2: true | G2: 2013-03-20T18:30:00.000Z | H2: 2025-11-07T10:42:37.675Z | I2: 2025-11-07T10:42:37.587Z | J2: https://www.infomerics.com/pressrelease/ | K2: air-perfection | L2: =J2&M2 -> https://www.infomerics.com/pressrelease/ | Q2: 2 | R2: yg0r8xoabi2nh72hqsuefyv6 | S2: Other | T2: true | U2: 2025-04-01T06:06:11.255Z | V2: 2025-04-01T06:06:11.255Z | W2: 2025-04-01T06:06:11.251Z
A3: 4482 | B3: yf552pthwveqfbtj98an88bc | C3: Uniproducts India Limited | D3: =VLOOKUP(C3,'Scraped data '!A:A,1,0) -> Uniproducts India Limited | F3: true | G3: 2013-03-20T18:30:00.000Z | H3: 2025-11-07T10:42:38.552Z | I3: 2025-11-07T10:42:38.520Z | J3: https://www.infomerics.com/pressrelease/ | K3: uniproducts-india-limited | Q3: 2 | R3: yg0r8xoabi2nh72hqsuefyv6 | S3: Other | T3: true | U3: 2025-04-01T06:06:11.255Z | V3: 2025-04-01T06:06:11.255Z | W3: 2025-04-01T06:06:11.251Z
A4: 4483 | B4: vq1mdxcr1ucxsy6wtsyehmhl | C4: Mitsumi Housing Private Limited | D4: =VLOOKUP(C4,'Scraped data '!A:A,1,0) -> Mitsumi Housing Private Limited | F4: true | G4: 2013-03-20T18:30:00.000Z | H4: 2025-11-07T10:42:39.384Z | I4: 2025-11-07T10:42:39.350Z | J4: https://www.infomerics.com/pressrelease/ | K4: mitsumi-housing-private-limited | Q4: 2 | R4: yg0r8xoabi2nh72hqsuefyv6 | S4: Other | T4: true | U4: 2025-04-01T06:06:11.255Z | V4: 2025-04-01T06:06:11.255Z | W4: 2025-04-01T06:06:11.251Z
A5: 4484 | B5: khscysv5z044po2ebdpqvmep | C5: Grand Canyon SEZ Private Limited | D5: =VLOOKUP(C5,'Scraped data '!A:A,1,0) -> Grand Canyon SEZ Private Limited | F5: true | G5: 2013-03-20T18:30:00.000Z | H5: 2025-11-07T10:42:42.645Z | I5: 2025-11-07T10:42:42.563Z | J5: https://www.infomerics.com/pressrelease/ | K5: grand-canyon-sez-private-limited | Q5: 2 | R5: yg0r8xoabi2nh72hqsuefyv6 | S5: Other | T5: true | U5: 2025-04-01T06:06:11.255Z | V5: 2025-04-01T06:06:11.255Z | W5: 2025-04-01T06:06:11.251Z
A6: 4485 | B6: z2jr5teujbcixtp9jpmq9gjs | C6: Nayati Medical Private Limited (Formerly known as Nayati Pharma Private Limited) | D6: =VLOOKUP(C6,'Scraped data '!A:A,1,0) -> Nayati Medical Private Limited (Formerly known as Nayati Pharma Private Limited) | F6: true | G6: 2014-03-20T18:30:00.000Z | H6: 2025-11-07T10:42:45.964Z | I6: 2025-11-07T10:42:45.877Z | J6: https://www.infomerics.com/pressrelease/ | K6: nayati-medical-private-limited-(formerly-known-as-nayati-pharma-private-limited) | Q6: 2 | R6: yg0r8xoabi2nh72hqsuefyv6 | S6: Other | T6: true | U6: 2025-04-01T06:06:11.255Z | V6: 2025-04-01T06:06:11.255Z | W6: 2025-04-01T06:06:11.251Z
A7: 4486 | B7: fnrzkvsgdt5psiinavmekfsd | C7: Suraksha Asset Reconstruction Private Limited (SARPL) | D7: =VLOOKUP(C7,'Scraped data '!A:A,1,0) -> Suraksha Asset Reconstruction Private Limited (SARPL) | F7: true | G7: 2014-03-20T18:30:00.000Z | H7: 2025-11-07T10:42:47.416Z | I7: 2025-11-07T10:42:47.366Z | J7: https://www.infomerics.com/pressrelease/ | K7: suraksha-asset-reconstruction-private-limited-(sarpl) | Q7: 2 | R7: yg0r8xoabi2nh72hqsuefyv6 | S7: Other | T7: true | U7: 2025-04-01T06:06:11.255Z | V7: 2025-04-01T06:06:11.255Z | W7: 2025-04-01T06:06:11.251Z
A8: 4487 | B8: jf5hici3wiauhf3c622lj8j9 | C8: Unimed Technologies Limited | D8: =VLOOKUP(C8,'Scraped data '!A:A,1,0) -> Unimed Technologies Limited | F8: true | G8: 2015-03-20T18:30:00.000Z | H8: 2025-11-07T10:42:48.641Z | I8: 2025-11-07T10:42:48.605Z | J8: https://www.infomerics.com/pressrelease/ | K8: unimed-technologies-limited | Q8: 2 | R8: yg0r8xoabi2nh72hqsuefyv6 | S8: Other | T8: true | U8: 2025-04-01T06:06:11.255Z | V8: 2025-04-01T06:06:11.255Z | W8: 2025-04-01T06:06:11.251Z
A9: 4488 | B9: llx26z5m2dz84hoajqbi6ghn | C9: MJ Pharmaceuticals Private Limited | D9: =VLOOKUP(C9,'Scraped data '!A:A,1,0) -> MJ Pharmaceuticals Private Limited | F9: true | G9: 2015-03-20T18:30:00.000Z | H9: 2025-11-07T10:42:49.804Z | I9: 2025-11-07T10:42:49.768Z | J9: https://www.infomerics.com/pressrelease/ | K9: mj-pharmaceuticals-private-limited | Q9: 2 | R9: yg0r8xoabi2nh72hqsuefyv6 | S9: Other | T9: true | U9: 2025-04-01T06:06:11.255Z | V9: 2025-04-01T06:06:11.255Z | W9: 2025-04-01T06:06:11.251Z
A10: 4489 | B10: mkiemvu9tb72h37c90z4hqr2 | C10: Aditya Medisales Limited | D10: =VLOOKUP(C10,'Scraped data '!A:A,1,0) -> Aditya Medisales Limited | F10: true | G10: 2015-03-20T18:30:00.000Z | H10: 2025-11-07T10:42:50.615Z | I10: 2025-11-07T10:42:50.588Z | J10: https://www.infomerics.com/pressrelease/ | K10: aditya-medisales-limited | Q10: 2 | R10: yg0r8xoabi2nh72hqsuefyv6 | S10: Other | T10: true | U10: 2025-04-01T06:06:11.255Z | V10: 2025-04-01T06:06:11.255Z | W10: 2025-04-01T06:06:11.251Z
A11: 4490 | B11: cr5x1da9hh1xmpst7gia9x2l | C11: Royal Realtors | D11: =VLOOKUP(C11,'Scraped data '!A:A,1,0) -> Royal Realtors | F11: true | G11: 2015-03-20T18:30:00.000Z | H11: 2025-11-07T10:42:51.538Z | I11: 2025-11-07T10:42:51.511Z | J11: https://www.infomerics.com/pressrelease/ | K11: royal-realtors | Q11: 2 | R11: yg0r8xoabi2nh72hqsuefyv6 | S11: Other | T11: true | U11: 2025-04-01T06:06:11.255Z | V11: 2025-04-01T06:06:11.255Z | W11: 2025-04-01T06:06:11.251Z
A12: 4491 | B12: g0qhpi9ygvcqsprm3sn035z8 | C12: India Mega Agro Anaj Limited | D12: =VLOOKUP(C12,'Scraped data '!A:A,1,0) -> India Mega Agro Anaj Limited | F12: true | G12: 2016-03-20T18:30:00.000Z | H12: 2025-12-01T13:44:33.631Z | I12: 2025-12-01T13:44:33.330Z | J12: https://www.infomerics.com/pressrelease/ | K12: india-mega-agro-anaj-limited | Q12: 2 | R12: yg0r8xoabi2nh72hqsuefyv6 | S12: Other | T12: true | U12: 2025-04-01T06:06:11.255Z | V12: 2025-04-01T06:06:11.255Z | W12: 2025-04-01T06:06:11.251Z
A13: 4492 | B13: lznynmfhw44i1y3cflhwjugd | C13: Yadu Sugar Limited | D13: =VLOOKUP(C13,'Scraped data '!A:A,1,0) -> Yadu Sugar Limited | F13: true | G13: 2016-03-20T18:30:00.000Z | H13: 2025-12-18T05:34:31.845Z | I13: 2025-12-18T05:34:31.529Z | J13: https://www.infomerics.com/pressrelease/ | K13: yadu-sugar-limited | Q13: 2 | R13: yg0r8xoabi2nh72hqsuefyv6 | S13: Other | T13: true | U13: 2025-04-01T06:06:11.255Z | V13: 2025-04-01T06:06:11.255Z | W13: 2025-04-01T06:06:11.251Z
A14: 4493 | B14: rzc8eoeebcn9twcdafed52us | C14: Shah Nanji Nagsi Export Private Limited | D14: =VLOOKUP(C14,'Scraped data '!A:A,1,0) -> Shah Nanji Nagsi Export Private Limited | F14: true | G14: 2016-03-20T18:30:00.000Z | H14: 2025-11-07T10:43:00.567Z | I14: 2025-11-07T10:43:00.497Z | J14: https://www.infomerics.com/pressrelease/ | K14: shah-nanji-nagsi-export-private-limited | Q14: 2 | R14: yg0r8xoabi2nh72hqsuefyv6 | S14: Other | T14: true | U14: 2025-04-01T06:06:11.255Z | V14: 2025-04-01T06:06:11.255Z | W14: 2025-04-01T06:06:11.251Z
... A880: 5359 | B880: dbnrhl4ee61s7vny50pb8zlx | C880: Viraj Profiles Private Limited (Erstwhile Viraj Profiles Limited) | D880: =VLOOKUP(C880,'Scraped data '!A:A,1,0) -> Viraj Profiles Private Limited (Erstwhile Viraj Profiles Limited) | F880: true | G880: 2005-11-20T18:30:00.000Z | H880: 2025-11-07T11:26:54.008Z | I880: 2025-11-07T11:26:53.888Z | J880: https://www.infomerics.com/pressrelease/ | K880: viraj-profiles-private-limited-erstwhile-viraj-profiles-limited | Q880: 2 | R880: yg0r8xoabi2nh72hqsuefyv6 | S880: Other | T880: true | U880: 2025-04-01T06:06:11.255Z | V880: 2025-04-01T06:06:11.255Z | W880: 2025-04-01T06:06:11.251Z
A881: 5360 | B881: a493jwp6xec54vc0x8p2y4ll | C881: K&R Rail Engineering Limited | D881: =VLOOKUP(C881,'Scraped data '!A:A,1,0) -> K&R Rail Engineering Limited | F881: true | G881: 2005-11-20T18:30:00.000Z | H881: 2025-11-20T10:11:17.743Z | I881: 2025-11-20T10:11:17.447Z | J881: https://www.infomerics.com/pressrelease/ | K881: kr-rail-engineering-limited
A882: 5361 | B882: w6ly8l8qsrmhm758jhpu3yup | C882: Optiemus Infracom Limited | D882: =VLOOKUP(C882,'Scraped data '!A:A,1,0) -> Optiemus Infracom Limited | F882: true | G882: 2005-11-20T18:30:00.000Z | H882: 2025-11-07T11:26:58.082Z | I882: 2025-11-07T11:26:58.047Z | J882: https://www.infomerics.com/pressrelease/ | K882: optiemus-infracom-limited | Q882: 2 | R882: yg0r8xoabi2nh72hqsuefyv6 | S882: Other | T882: true | U882: 2025-04-01T06:06:11.255Z | V882: 2025-04-01T06:06:11.255Z | W882: 2025-04-01T06:06:11.251Z
A883: 5362 | B883: vwhbfnkz3wpqve40mfdr7ax0 | C883: Amar Shakti Commerce & Industries Limited | D883: =VLOOKUP(C883,'Scraped data '!A:A,1,0) -> Amar Shakti Commerce & Industries Limited | F883: true | G883: 2006-11-20T18:30:00.000Z | H883: 2025-11-25T12:09:53.430Z | I883: 2025-11-25T12:09:53.266Z | J883: https://www.infomerics.com/pressrelease/ | K883: amar-shakti-commerce--industries-limited | Q883: 2 | R883: yg0r8xoabi2nh72hqsuefyv6 | S883: Other | T883: true | U883: 2025-04-01T06:06:11.255Z | V883: 2025-04-01T06:06:11.255Z | W883: 2025-04-01T06:06:11.251Z
A884: 5363 | B884: xgiyt3wu5gf2m6gwa3y5i2ua | C884: Spray Engineering Devices Limited | D884: =VLOOKUP(C884,'Scraped data '!A:A,1,0) -> Spray Engineering Devices Limited | F884: true | G884: 2006-11-20T18:30:00.000Z | H884: 2025-11-07T11:27:04.243Z | I884: 2025-11-07T11:27:04.148Z | J884: https://www.infomerics.com/pressrelease/ | K884: spray-engineering-devices-limited | Q884: 2 | R884: yg0r8xoabi2nh72hqsuefyv6 | S884: Other | T884: true | U884: 2025-04-01T06:06:11.255Z | V884: 2025-04-01T06:06:11.255Z | W884: 2025-04-01T06:06:11.251Z
A885: 5364 | B885: kvkrtzcq2jietztgyug89fmi | C885: Mono Steel India Limited | D885: =VLOOKUP(C885,'Scraped data '!A:A,1,0) -> Mono Steel India Limited | F885: true | G885: 2006-11-20T18:30:00.000Z | H885: 2025-11-07T11:27:07.598Z | I885: 2025-11-07T11:27:07.524Z | J885: https://www.infomerics.com/pressrelease/ | K885: mono-steel-india-limited | Q885: 2 | R885: yg0r8xoabi2nh72hqsuefyv6 | S885: Other | T885: true | U885: 2025-04-01T06:06:11.255Z | V885: 2025-04-01T06:06:11.255Z | W885: 2025-04-01T06:06:11.251Z
A886: 5365 | B886: s7spm8flqm8o189bnzb7ujob | C886: BFG International Private Limited | D886: =VLOOKUP(C886,'Scraped data '!A:A,1,0) -> BFG International Private Limited | F886: true | G886: 2006-11-20T18:30:00.000Z | H886: 2025-11-07T11:27:10.482Z | I886: 2025-11-07T11:27:10.388Z | J886: https://www.infomerics.com/pressrelease/ | K886: bfg-international-private-limited | Q886: 2 | R886: yg0r8xoabi2nh72hqsuefyv6 | S886: Other | T886: true | U886: 2025-04-01T06:06:11.255Z | V886: 2025-04-01T06:06:11.255Z | W886: 2025-04-01T06:06:11.251Z
A887: 5366 | B887: khxzkjtxfp8fiw9uw5pzntgj | C887: Lifeline Multi Ventures Private Limited | D887: =VLOOKUP(C887,'Scraped data '!A:A,1,0) -> Lifeline Multi Ventures Private Limited | F887: true | G887: 2007-11-20T18:30:00.000Z | H887: 2025-11-07T11:27:13.726Z | I887: 2025-11-07T11:27:13.651Z | J887: https://www.infomerics.com/pressrelease/ | K887: lifeline-multi-ventures-private-limited | Q887: 2 | R887: yg0r8xoabi2nh72hqsuefyv6 | S887: Other | T887: true | U887: 2025-04-01T06:06:11.255Z | V887: 2025-04-01T06:06:11.255Z | W887: 2025-04-01T06:06:11.251Z
A888: 5367 | B888: nhqei8vx2x8gmzg4rgypptle | C888: Chadha Papers Limited | D888: =VLOOKUP(C888,'Scraped data '!A:A,1,0) -> Chadha Papers Limited | F888: true | G888: 2008-11-20T18:30:00.000Z | H888: 2025-11-07T11:27:17.156Z | I888: 2025-11-07T11:27:17.081Z | J888: https://www.infomerics.com/pressrelease/ | K888: chadha-papers-limited | Q888: 2 | R888: yg0r8xoabi2nh72hqsuefyv6 | S888: Other | T888: true | U888: 2025-04-01T06:06:11.255Z | V888: 2025-04-01T06:06:11.255Z | W888: 2025-04-01T06:06:11.251Z
A889: 5368 | B889: g9rdfmrlegl54olb33wh22w1 | C889: Shri Bajrang Power & Ispat Limited | D889: =VLOOKUP(C889,'Scraped data '!A:A,1,0) -> Shri Bajrang Power & Ispat Limited | F889: true | G889: 2008-11-20T18:30:00.000Z | H889: 2025-11-07T11:27:20.775Z | I889: 2025-11-07T11:27:20.692Z | J889: https://www.infomerics.com/pressrelease/ | K889: shri-bajrang-power-ispat-limited | Q889: 2 | R889: yg0r8xoabi2nh72hqsuefyv6 | S889: Other | T889: true | U889: 2025-04-01T06:06:11.255Z | V889: 2025-04-01T06:06:11.255Z | W889: 2025-04-01T06:06:11.251Z
A890: 5369 | B890: vn5bm2y0616wf01mzh7t8g3n | C890: Amitex Agro Product Private Limited | D890: =VLOOKUP(C890,'Scraped data '!A:A,1,0) -> Amitex Agro Product Private Limited | F890: true | G890: 2008-11-20T18:30:00.000Z | H890: 2025-11-07T11:27:23.881Z | I890: 2025-11-07T11:27:23.758Z | J890: https://www.infomerics.com/pressrelease/ | K890: amitex-agro-product-private-limited | Q890: 2 | R890: yg0r8xoabi2nh72hqsuefyv6 | S890: Other | T890: true | U890: 2025-04-01T06:06:11.255Z | V890: 2025-04-01T06:06:11.255Z | W890: 2025-04-01T06:06:11.251Z
A891: 5370 | B891: ijzlydol1z3gmqydledt3gw0 | C891: Maa Harsiddhi Infra Developers Private Limited | D891: =VLOOKUP(C891,'Scraped data '!A:A,1,0) -> Maa Harsiddhi Infra Developers Private Limited | F891: true | G891: 2009-11-20T18:30:00.000Z | H891: 2025-11-07T11:27:27.626Z | I891: 2025-11-07T11:27:27.543Z | J891: https://www.infomerics.com/pressrelease/ | K891: maa-harsiddhi-infra-developers-private-limited | Q891: 2 | R891: yg0r8xoabi2nh72hqsuefyv6 | S891: Other | T891: true | U891: 2025-04-01T06:06:11.255Z | V891: 2025-04-01T06:06:11.255Z | W891: 2025-04-01T06:06:11.251Z
A892: 5371 | B892: lknjspyej8kjvob7iiz40z22 | C892: Sindhu Cargo Services Private Limited | D892: =VLOOKUP(C892,'Scraped data '!A:A,1,0) -> Sindhu Cargo Services Private Limited | F892: true | G892: 2009-11-20T18:30:00.000Z | H892: 2025-11-07T11:27:29.841Z | I892: 2025-11-07T11:27:29.770Z | J892: https://www.infomerics.com/pressrelease/ | K892: sindhu-cargo-services-private-limited | Q892: 2 | R892: yg0r8xoabi2nh72hqsuefyv6 | S892: Other | T892: true | U892: 2025-04-01T06:06:11.255Z | V892: 2025-04-01T06:06:11.255Z | W892: 2025-04-01T06:06:11.251Z
A893: 5372 | B893: qzh52cfrklkgaojhw61x6jl3 | C893: Scan Steels Limited | D893: =VLOOKUP(C893,'Scraped data '!A:A,1,0) -> Scan Steels Limited | F893: true | G893: 2009-11-20T18:30:00.000Z | H893: 2025-11-07T11:27:34.866Z | I893: 2025-11-07T11:27:34.695Z | J893: https://www.infomerics.com/pressrelease/ | K893: scan-steels-limited | Q893: 2 | R893: yg0r8xoabi2nh72hqsuefyv6 | S893: Other | T893: true | U893: 2025-04-01T06:06:11.255Z | V893: 2025-04-01T06:06:11.255Z | W893: 2025-04-01T06:06:11.251Z
... A1237: 5717 | B1237: y8jmcne01b5cs262aqgkaxxi | C1237: Bank Of India | D1237: =VLOOKUP(C1237,'Scraped data '!A:A,1,0) -> Bank Of India | F1237: true | G1237: 2021-09-20T20:32:26.000Z | H1237: 2025-11-07T11:43:21.868Z | I1237: 2025-11-07T11:43:21.814Z | J1237: https://www.infomerics.com/pressrelease/ | K1237: bank-of-india | Q1237: 2 | R1237: yg0r8xoabi2nh72hqsuefyv6 | S1237: Other | T1237: true | U1237: 2025-04-01T06:06:11.255Z | V1237: 2025-04-01T06:06:11.255Z | W1237: 2025-04-01T06:06:11.251Z
A1238: 5718 | B1238: tz81x50crakj43nav2gbmm4a | C1238: Babulal Edible Oil Private Limited | D1238: today | F1238: true | G1238: 2021-09-20T21:10:02.000Z | H1238: 2025-11-07T11:43:23.576Z | I1238: 2025-11-07T11:43:23.530Z | J1238: https://www.infomerics.com/pressrelease/ | K1238: babulal-edible-oil-private-limited | Q1238: 2 | R1238: yg0r8xoabi2nh72hqsuefyv6 | S1238: Other | T1238: true | U1238: 2025-04-01T06:06:11.255Z | V1238: 2025-04-01T06:06:11.255Z | W1238: 2025-04-01T06:06:11.251Z
A1239: 5719 | B1239: tl8ubv0sfywp8mjs24ns6bth | C1239: Data Ingenious Global Limited | D1239: =VLOOKUP(C1239,'Scraped data '!A:A,1,0) -> Data Ingenious Global Limited | F1239: true | G1239: 2021-09-20T21:15:37.000Z | H1239: 2025-11-07T11:43:25.293Z | I1239: 2025-11-07T11:43:25.247Z | J1239: https://www.infomerics.com/pressrelease/ | K1239: data-ingenious-global-limited | Q1239: 2 | R1239: yg0r8xoabi2nh72hqsuefyv6 | S1239: Other | T1239: true | U1239: 2025-04-01T06:06:11.255Z | V1239: 2025-04-01T06:06:11.255Z | W1239: 2025-04-01T06:06:11.251Z
A1240: 5720 | B1240: fdzsiec7k7hwix9f4ik5dx3q | C1240: Ritika Vegitables Oil Private Limited | D1240: =VLOOKUP(C1240,'Scraped data '!A:A,1,0) -> #N/A | F1240: true | G1240: 2021-09-20T21:22:14.000Z | H1240: 2025-11-07T11:43:27.019Z | I1240: 2025-11-07T11:43:26.974Z | J1240: https://www.infomerics.com/pressrelease/ | K1240: ritika-vegitables-oil-private-limited | Q1240: 2 | R1240: yg0r8xoabi2nh72hqsuefyv6 | S1240: Other | T1240: true | U1240: 2025-04-01T06:06:11.255Z | V1240: 2025-04-01T06:06:11.255Z | W1240: 2025-04-01T06:06:11.251Z
A1241: 5721 | B1241: cun3fozvntsc1zxfpe73vuj0 | C1241: Shree Hari Agro Industries Limited | D1241: =VLOOKUP(C1241,'Scraped data '!A:A,1,0) -> Shree Hari Agro Industries Limited | F1241: true | G1241: 2021-09-20T21:26:56.000Z | H1241: 2025-11-07T11:43:28.962Z | I1241: 2025-11-07T11:43:28.908Z | J1241: https://www.infomerics.com/pressrelease/ | K1241: shree-hari-agro-industries-limited | Q1241: 2 | R1241: yg0r8xoabi2nh72hqsuefyv6 | S1241: Other | T1241: true | U1241: 2025-04-01T06:06:11.255Z | V1241: 2025-04-01T06:06:11.255Z | W1241: 2025-04-01T06:06:11.251Z
A1242: 5722 | B1242: ra6qasqj7wgjtn7w04pj77q7 | C1242: Vijayneha Polymers Private Limited | D1242: =VLOOKUP(C1242,'Scraped data '!A:A,1,0) -> Vijayneha Polymers Private Limited | F1242: true | G1242: 2021-09-22T07:04:22.000Z | H1242: 2026-01-22T11:49:48.918Z | I1242: 2026-01-22T11:49:48.736Z | J1242: https://www.infomerics.com/pressrelease/ | K1242: vijayneha-polymers-private-limited | Q1242: 2 | R1242: yg0r8xoabi2nh72hqsuefyv6 | S1242: Other | T1242: true | U1242: 2025-04-01T06:06:11.255Z | V1242: 2025-04-01T06:06:11.255Z | W1242: 2025-04-01T06:06:11.251Z
A1243: 5723 | B1243: dmcxfj8hwi2uqokcfa7cmdf6 | C1243: SBL Energy Limited | D1243: =VLOOKUP(C1243,'Scraped data '!A:A,1,0) -> SBL Energy Limited | F1243: true | G1243: 2021-09-21T20:42:25.000Z | H1243: 2025-11-07T11:43:35.488Z | I1243: 2025-11-07T11:43:35.400Z | J1243: https://www.infomerics.com/pressrelease/ | K1243: sbl-energy-limited | Q1243: 2 | R1243: yg0r8xoabi2nh72hqsuefyv6 | S1243: Other | T1243: true | U1243: 2025-04-01T06:06:11.255Z | V1243: 2025-04-01T06:06:11.255Z | W1243: 2025-04-01T06:06:11.251Z
A1244: 5724 | B1244: c7uj8ozza9b774pt90ii1mqf | C1244: Brij Gopal Construction Company Private Limited | D1244: =VLOOKUP(C1244,'Scraped data '!A:A,1,0) -> Brij Gopal Construction Company Private Limited | F1244: true | G1244: 2021-09-21T22:19:01.000Z | H1244: 2025-11-07T11:43:38.514Z | I1244: 2025-11-07T11:43:38.453Z | J1244: https://www.infomerics.com/pressrelease/ | K1244: brij-gopal-construction-company-private-limited | Q1244: 2 | R1244: yg0r8xoabi2nh72hqsuefyv6 | S1244: Other | T1244: true | U1244: 2025-04-01T06:06:11.255Z | V1244: 2025-04-01T06:06:11.255Z | W1244: 2025-04-01T06:06:11.251Z
A1245: 5725 | B1245: waybar8xdxif3zmbjfdp71gp | C1245: Diwakar Enterprises Private Limited | D1245: =VLOOKUP(C1245,'Scraped data '!A:A,1,0) -> Diwakar Enterprises Private Limited | F1245: true | G1245: 2021-09-21T22:28:17.000Z | H1245: 2025-11-07T11:43:40.261Z | I1245: 2025-11-07T11:43:40.221Z | J1245: https://www.infomerics.com/pressrelease/ | K1245: diwakar-enterprises-private-limited | Q1245: 2 | R1245: yg0r8xoabi2nh72hqsuefyv6 | S1245: Other | T1245: true | U1245: 2025-04-01T06:06:11.255Z | V1245: 2025-04-01T06:06:11.255Z | W1245: 2025-04-01T06:06:11.251Z
A1246: 5726 | B1246: vst2axjnkpemwt5rx4uflbf7 | C1246: Chintpurni Steel Private Limited | D1246: =VLOOKUP(C1246,'Scraped data '!A:A,1,0) -> Chintpurni Steel Private Limited | F1246: true | G1246: 2021-09-21T23:45:03.000Z | H1246: 2025-11-07T11:43:42.748Z | I1246: 2025-11-07T11:43:42.685Z | J1246: https://www.infomerics.com/pressrelease/ | K1246: chintpurni-steel-private-limited | Q1246: 2 | R1246: yg0r8xoabi2nh72hqsuefyv6 | S1246: Other | T1246: true | U1246: 2025-04-01T06:06:11.255Z | V1246: 2025-04-01T06:06:11.255Z | W1246: 2025-04-01T06:06:11.251Z
A1247: 5727 | B1247: hp4pinabui1xkk6efvodhnfw | C1247: Narsimha Iron and Steel Private Limited | D1247: =VLOOKUP(C1247,'Scraped data '!A:A,1,0) -> Narsimha Iron and Steel Private Limited | F1247: true | G1247: 2021-09-21T23:48:39.000Z | H1247: 2025-11-07T11:43:45.144Z | I1247: 2025-11-07T11:43:45.088Z | J1247: https://www.infomerics.com/pressrelease/ | K1247: narsimha-iron-and-steel-private-limited | Q1247: 2 | R1247: yg0r8xoabi2nh72hqsuefyv6 | S1247: Other | T1247: true | U1247: 2025-04-01T06:06:11.255Z | V1247: 2025-04-01T06:06:11.255Z | W1247: 2025-04-01T06:06:11.251Z
A1248: 5728 | B1248: bve176ijply4hk3cw8my7pct | C1248: Clifton Export Private Limited | D1248: =VLOOKUP(C1248,'Scraped data '!A:A,1,0) -> Clifton Export Private Limited | F1248: true | G1248: 2021-09-22T23:35:29.000Z | H1248: 2025-11-07T11:43:47.751Z | I1248: 2025-11-07T11:43:47.699Z | J1248: https://www.infomerics.com/pressrelease/ | K1248: clifton-export-private-limited | Q1248: 2 | R1248: yg0r8xoabi2nh72hqsuefyv6 | S1248: Other | T1248: true | U1248: 2025-04-01T06:06:11.255Z | V1248: 2025-04-01T06:06:11.255Z | W1248: 2025-04-01T06:06:11.251Z
A1249: 5729 | B1249: ubaem7zxtoeu3jzsqxxnm712 | C1249: Bombay Education Trust | D1249: =VLOOKUP(C1249,'Scraped data '!A:A,1,0) -> Bombay Education Trust | F1249: true | G1249: 2021-09-23T23:40:43.000Z | H1249: 2025-11-07T11:43:50.597Z | I1249: 2025-11-07T11:43:50.539Z | J1249: https://www.infomerics.com/pressrelease/ | K1249: bombay-education-trust | Q1249: 2 | R1249: yg0r8xoabi2nh72hqsuefyv6 | S1249: Other | T1249: true | U1249: 2025-04-01T06:06:11.255Z | V1249: 2025-04-01T06:06:11.255Z | W1249: 2025-04-01T06:06:11.251Z
A1250: 5730 | B1250: ad2fb5g4qasdg0fqbpm3vu8x | C1250: Sahyog Charitable Trust | D1250: =VLOOKUP(C1250,'Scraped data '!A:A,1,0) -> Sahyog Charitable Trust | F1250: true | G1250: 2021-09-23T23:44:27.000Z | H1250: 2025-11-07T11:43:53.228Z | I1250: 2025-11-07T11:43:53.173Z | J1250: https://www.infomerics.com/pressrelease/ | K1250: sahyog-charitable-trust | Q1250: 2 | R1250: yg0r8xoabi2nh72hqsuefyv6 | S1250: Other | T1250: true | U1250: 2025-04-01T06:06:11.255Z | V1250: 2025-04-01T06:06:11.255Z | W1250: 2025-04-01T06:06:11.251Z
... A1719: 6199 | B1719: jv50cwj5p355z9t2vinpjt5j | C1719: Master Capital Services Limited | D1719: =VLOOKUP(C1719,'Scraped data '!A:A,1,0) -> Master Capital Services Limited | F1719: true | G1719: 2022-09-08T13:18:11.000Z | H1719: 2025-11-07T12:03:27.097Z | I1719: 2025-11-07T12:03:27.058Z | J1719: https://www.infomerics.com/pressrelease/ | K1719: master-capital-services-limited- | Q1719: 2 | R1719: yg0r8xoabi2nh72hqsuefyv6 | S1719: Other | T1719: true | U1719: 2025-04-01T06:06:11.255Z | V1719: 2025-04-01T06:06:11.255Z | W1719: 2025-04-01T06:06:11.251Z
A1720: 6200 | B1720: b44zb4k6wtzt5sqi1abzg0yf | C1720: Kalyani Transco Private Limited | D1720: today | F1720: true | G1720: 2022-09-08T13:27:52.000Z | H1720: 2025-11-07T12:03:29.515Z | I1720: 2025-11-07T12:03:29.425Z | J1720: https://www.infomerics.com/pressrelease/ | K1720: kalyani-transco-private-limited | Q1720: 2 | R1720: yg0r8xoabi2nh72hqsuefyv6 | S1720: Other | T1720: true | U1720: 2025-04-01T06:06:11.255Z | V1720: 2025-04-01T06:06:11.255Z | W1720: 2025-04-01T06:06:11.251Z
A1721: 6201 | B1721: lszy290sb9f2fccmd6r8hdvn | C1721: Mauli Metal Industries Private Limited | D1721: =VLOOKUP(C1721,'Scraped data '!A:A,1,0) -> Mauli Metal Industries Private Limited | F1721: true | G1721: 2022-09-12T06:45:50.000Z | H1721: 2025-12-12T09:25:05.940Z | I1721: 2025-12-12T09:25:05.778Z | J1721: https://www.infomerics.com/pressrelease/ | K1721: mauli-metal-industries-private-limited | Q1721: 2 | R1721: yg0r8xoabi2nh72hqsuefyv6 | S1721: Other | T1721: true | U1721: 2025-04-01T06:06:11.255Z | V1721: 2025-04-01T06:06:11.255Z | W1721: 2025-04-01T06:06:11.251Z
A1722: 6202 | B1722: jfmvcptjep6zj4ngv2vu66k4 | C1722: Vikas Ecotech Limited | D1722: =VLOOKUP(C1722,'Scraped data '!A:A,1,0) -> Vikas Ecotech Limited | F1722: true | G1722: 2022-09-13T10:49:22.000Z | H1722: 2025-11-07T12:03:33.548Z | I1722: 2025-11-07T12:03:33.506Z | J1722: https://www.infomerics.com/pressrelease/ | K1722: vikas-ecotech-limited | Q1722: 2 | R1722: yg0r8xoabi2nh72hqsuefyv6 | S1722: Other | T1722: true | U1722: 2025-04-01T06:06:11.255Z | V1722: 2025-04-01T06:06:11.255Z | W1722: 2025-04-01T06:06:11.251Z
A1723: 6203 | B1723: hck8ndita6vjkdtg0thdevm2 | C1723: C.G. Ispat Private Limited (CGIPL) | D1723: =VLOOKUP(C1723,'Scraped data '!A:A,1,0) -> C.G. Ispat Private Limited (CGIPL) | F1723: true | G1723: 2022-09-15T10:17:10.000Z | H1723: 2025-11-07T12:03:35.083Z | I1723: 2025-11-07T12:03:35.041Z | J1723: https://www.infomerics.com/pressrelease/ | K1723: cg-ispat-private-limited-cgipl | Q1723: 2 | R1723: yg0r8xoabi2nh72hqsuefyv6 | S1723: Other | T1723: true | U1723: 2025-04-01T06:06:11.255Z | V1723: 2025-04-01T06:06:11.255Z | W1723: 2025-04-01T06:06:11.251Z
A1724: 6204 | B1724: gwrnplvdnchiobgg3g6mcm1f | C1724: Arthmate Financing India Private Limited (Mamta Projects Private Limited) | D1724: =VLOOKUP(C1724,'Scraped data '!A:A,1,0) -> Arthmate Financing India Private Limited (Mamta Projects Private Limited) | F1724: true | G1724: 2022-09-15T12:29:18.000Z | H1724: 2025-11-07T12:03:40.402Z | I1724: 2025-11-07T12:03:40.287Z | J1724: https://www.infomerics.com/pressrelease/ | K1724: arthmate-financing-india-private-limited-mamta-projects-private-limited | Q1724: 2 | R1724: yg0r8xoabi2nh72hqsuefyv6 | S1724: Other | T1724: true | U1724: 2025-04-01T06:06:11.255Z | V1724: 2025-04-01T06:06:11.255Z | W1724: 2025-04-01T06:06:11.251Z
A1725: 6205 | B1725: nh0pu6jg8tle2ioc0dao816v | C1725: Kedsati Iron & Steel Private Limited | D1725: =VLOOKUP(C1725,'Scraped data '!A:A,1,0) -> Kedsati Iron & Steel Private Limited | F1725: true | G1725: 2022-09-16T12:39:01.000Z | H1725: 2025-11-07T12:03:42.537Z | I1725: 2025-11-07T12:03:42.485Z | J1725: https://www.infomerics.com/pressrelease/ | K1725: kedsati-iron--steel-private-limited | Q1725: 2 | R1725: yg0r8xoabi2nh72hqsuefyv6 | S1725: Other | T1725: true | U1725: 2025-04-01T06:06:11.255Z | V1725: 2025-04-01T06:06:11.255Z | W1725: 2025-04-01T06:06:11.251Z
A1726: 6206 | B1726: pca148ru88lh6sytn30wjdlu | C1726: Fabro Forge | D1726: =VLOOKUP(C1726,'Scraped data '!A:A,1,0) -> Fabro Forge | F1726: true | G1726: 2022-09-16T12:39:21.000Z | H1726: 2025-11-07T12:03:44.197Z | I1726: 2025-11-07T12:03:44.154Z | J1726: https://www.infomerics.com/pressrelease/ | K1726: fabro-forge | Q1726: 2 | R1726: yg0r8xoabi2nh72hqsuefyv6 | S1726: Other | T1726: true | U1726: 2025-04-01T06:06:11.255Z | V1726: 2025-04-01T06:06:11.255Z | W1726: 2025-04-01T06:06:11.251Z
A1727: 6207 | B1727: ganjwjfufxhowo3ky4n43m6j | C1727: Eastern Track Udyog Private Limited | D1727: =VLOOKUP(C1727,'Scraped data '!A:A,1,0) -> Eastern Track Udyog Private Limited | F1727: true | G1727: 2022-09-16T12:39:45.000Z | H1727: 2025-11-07T12:03:46.992Z | I1727: 2025-11-07T12:03:46.924Z | J1727: https://www.infomerics.com/pressrelease/ | K1727: eastern-track-udyog-private-limited | Q1727: 2 | R1727: yg0r8xoabi2nh72hqsuefyv6 | S1727: Other | T1727: true | U1727: 2025-04-01T06:06:11.255Z | V1727: 2025-04-01T06:06:11.255Z | W1727: 2025-04-01T06:06:11.251Z
A1728: 6208 | B1728: qkrz3yi73mb5dkcowksiw56c | C1728: Smart Developers | D1728: =VLOOKUP(C1728,'Scraped data '!A:A,1,0) -> Smart Developers | F1728: true | G1728: 2022-09-16T13:04:31.000Z | H1728: 2025-11-07T12:03:48.665Z | I1728: 2025-11-07T12:03:48.630Z | J1728: https://www.infomerics.com/pressrelease/ | K1728: smart-developers | Q1728: 2 | R1728: yg0r8xoabi2nh72hqsuefyv6 | S1728: Other | T1728: true | U1728: 2025-04-01T06:06:11.255Z | V1728: 2025-04-01T06:06:11.255Z | W1728: 2025-04-01T06:06:11.251Z
A1729: 6209 | B1729: xo2pf3adfyl0akuhjcb6bq0b | C1729: Komarla Hatcheries | D1729: =VLOOKUP(C1729,'Scraped data '!A:A,1,0) -> Komarla Hatcheries | F1729: true | G1729: 2022-09-19T10:23:47.000Z | H1729: 2025-11-07T12:03:51.279Z | I1729: 2025-11-07T12:03:51.219Z | J1729: https://www.infomerics.com/pressrelease/ | K1729: komarla-hatcheries | Q1729: 2 | R1729: yg0r8xoabi2nh72hqsuefyv6 | S1729: Other | T1729: true | U1729: 2025-04-01T06:06:11.255Z | V1729: 2025-04-01T06:06:11.255Z | W1729: 2025-04-01T06:06:11.251Z
A1730: 6210 | B1730: tnus9pcyzc6eyul4cazl5di8 | C1730: Rayalaseema Steel Re Rolling Mills Private Limited | D1730: =VLOOKUP(C1730,'Scraped data '!A:A,1,0) -> Rayalaseema Steel Re Rolling Mills Private Limited | F1730: true | G1730: 2022-09-20T09:05:36.000Z | H1730: 2025-11-07T12:03:53.053Z | I1730: 2025-11-07T12:03:53.011Z | J1730: https://www.infomerics.com/pressrelease/ | K1730: rayalaseema-steel-re-rolling-mills-private-limited | Q1730: 2 | R1730: yg0r8xoabi2nh72hqsuefyv6 | S1730: Other | T1730: true | U1730: 2025-04-01T06:06:11.255Z | V1730: 2025-04-01T06:06:11.255Z | W1730: 2025-04-01T06:06:11.251Z
A1731: 6211 | B1731: c04l8tkbmlxa85yhilfhzftp | C1731: S & P feeds Private Limited | D1731: =VLOOKUP(C1731,'Scraped data '!A:A,1,0) -> S & P feeds Private Limited | F1731: true | G1731: 2022-09-20T13:06:20.000Z | H1731: 2026-02-06T11:27:05.356Z | I1731: 2026-02-06T11:27:05.170Z | J1731: https://www.infomerics.com/pressrelease/ | K1731: s--p-feeds-private-limited | Q1731: 2 | R1731: yg0r8xoabi2nh72hqsuefyv6 | S1731: Other | T1731: true | U1731: 2025-04-01T06:06:11.255Z | V1731: 2025-04-01T06:06:11.255Z | W1731: 2025-04-01T06:06:11.251Z
A1732: 6212 | B1732: ueyrncb7xpnl77ip5huv2c9y | C1732: ANS Private Limited | D1732: =VLOOKUP(C1732,'Scraped data '!A:A,1,0) -> ANS Private Limited | F1732: true | G1732: 2022-09-20T13:12:19.000Z | H1732: 2025-11-07T12:03:58.571Z | I1732: 2025-11-07T12:03:58.496Z | J1732: https://www.infomerics.com/pressrelease/ | K1732: ans-private-limited | Q1732: 2 | R1732: yg0r8xoabi2nh72hqsuefyv6 | S1732: Other | T1732: true | U1732: 2025-04-01T06:06:11.255Z | V1732: 2025-04-01T06:06:11.255Z | W1732: 2025-04-01T06:06:11.251Z
... A1748: 6228 | B1748: jrbesktcj2yvjcmkwoxtyk8q | C1748: Mahaprabhu Residency LLP | D1748: =VLOOKUP(C1748,'Scraped data '!A:A,1,0) -> Mahaprabhu Residency LLP | F1748: true | G1748: 2022-09-30T09:43:35.000Z | H1748: 2025-11-07T12:04:41.009Z | I1748: 2025-11-07T12:04:40.963Z | J1748: https://www.infomerics.com/pressrelease/ | K1748: mahaprabhu-residency-llp | Q1748: 2 | R1748: yg0r8xoabi2nh72hqsuefyv6 | S1748: Other | T1748: true | U1748: 2025-04-01T06:06:11.255Z | V1748: 2025-04-01T06:06:11.255Z | W1748: 2025-04-01T06:06:11.251Z
A1749: 6229 | B1749: mkdzr58eqq0rvjzy2odzt2nf | C1749: SP Sugar & Agro Private Limited | D1749: today | F1749: true | G1749: 2022-09-30T10:24:21.000Z | H1749: 2025-11-07T12:04:43.151Z | I1749: 2025-11-07T12:04:43.105Z | J1749: https://www.infomerics.com/pressrelease/ | K1749: sp-sugar--agro-private-limited | Q1749: 2 | R1749: yg0r8xoabi2nh72hqsuefyv6 | S1749: Other | T1749: true | U1749: 2025-04-01T06:06:11.255Z | V1749: 2025-04-01T06:06:11.255Z | W1749: 2025-04-01T06:06:11.251Z
A1750: 6230 | B1750: gu9fmlekvdt9saifn41bnq75 | C1750: Preca Solutions India Private Limited | D1750: =VLOOKUP(C1750,'Scraped data '!A:A,1,0) -> Preca Solutions India Private Limited | F1750: true | G1750: 2022-09-30T11:12:09.000Z | H1750: 2026-01-14T06:40:01.774Z | I1750: 2026-01-14T06:40:01.615Z | J1750: https://www.infomerics.com/pressrelease/ | K1750: preca-solutions-india-private-limited | Q1750: 2 | R1750: yg0r8xoabi2nh72hqsuefyv6 | S1750: Other | T1750: true | U1750: 2025-04-01T06:06:11.255Z | V1750: 2025-04-01T06:06:11.255Z | W1750: 2025-04-01T06:06:11.251Z
A1751: 6231 | B1751: q4l1mkap6lfcdfd4554937wr | C1751: Platinum Finleasing & Infra Development Private Limited | D1751: =VLOOKUP(C1751,'Scraped data '!A:A,1,0) -> Platinum Finleasing & Infra Development Private Limited | F1751: true | G1751: 2022-10-03T07:49:54.000Z | H1751: 2025-11-07T12:04:45.817Z | I1751: 2025-11-07T12:04:45.790Z | J1751: https://www.infomerics.com/pressrelease/ | K1751: platinum-finleasing--infra-development-private-limited | Q1751: 2 | R1751: yg0r8xoabi2nh72hqsuefyv6 | S1751: Other | T1751: true | U1751: 2025-04-01T06:06:11.255Z | V1751: 2025-04-01T06:06:11.255Z | W1751: 2025-04-01T06:06:11.251Z
A1752: 6232 | B1752: davbr5iw2cm8lqsz138h8q6e | C1752: Mayuri Broiler Breeding Farms Private Limited | D1752: =VLOOKUP(C1752,'Scraped data '!A:A,1,0) -> Mayuri Broiler Breeding Farms Private Limited | F1752: true | G1752: 2022-10-03T11:24:17.000Z | H1752: 2025-11-07T12:04:47.501Z | I1752: 2025-11-07T12:04:47.442Z | J1752: https://www.infomerics.com/pressrelease/ | K1752: mayuri-broiler-breeding-farms-private-limited | Q1752: 2 | R1752: yg0r8xoabi2nh72hqsuefyv6 | S1752: Other | T1752: true | U1752: 2025-04-01T06:06:11.255Z | V1752: 2025-04-01T06:06:11.255Z | W1752: 2025-04-01T06:06:11.251Z
A1753: 6233 | B1753: x86vd1a4fs0j01xt9k0wuyym | C1753: Arham Wealth Management Private Limited | D1753: =VLOOKUP(C1753,'Scraped data '!A:A,1,0) -> Arham Wealth Management Private Limited | F1753: true | G1753: 2022-10-04T10:31:54.000Z | H1753: 2025-11-07T12:04:49.672Z | I1753: 2025-11-07T12:04:49.618Z | J1753: https://www.infomerics.com/pressrelease/ | K1753: arham-wealth-management-private-limited | Q1753: 2 | R1753: yg0r8xoabi2nh72hqsuefyv6 | S1753: Other | T1753: true | U1753: 2025-04-01T06:06:11.255Z | V1753: 2025-04-01T06:06:11.255Z | W1753: 2025-04-01T06:06:11.251Z
A1754: 6234 | B1754: pyhfh1nbzpomjilte88ppxid | C1754: Paswara Papers Limited | D1754: =VLOOKUP(C1754,'Scraped data '!A:A,1,0) -> Paswara Papers Limited | F1754: true | G1754: 2022-10-06T11:18:36.000Z | H1754: 2025-11-07T12:04:51.716Z | I1754: 2025-11-07T12:04:51.664Z | J1754: https://www.infomerics.com/pressrelease/ | K1754: paswara-papers-limited | Q1754: 2 | R1754: yg0r8xoabi2nh72hqsuefyv6 | S1754: Other | T1754: true | U1754: 2025-04-01T06:06:11.255Z | V1754: 2025-04-01T06:06:11.255Z | W1754: 2025-04-01T06:06:11.251Z
A1755: 6235 | B1755: i9z9x53dgzh81mvq05lz5qpv | C1755: Ayyappa Infra Projects Private Limited | D1755: =VLOOKUP(C1755,'Scraped data '!A:A,1,0) -> Ayyappa Infra Projects Private Limited | F1755: true | G1755: 2022-10-07T07:31:11.000Z | H1755: 2025-11-07T12:04:54.210Z | I1755: 2025-11-07T12:04:54.156Z | J1755: https://www.infomerics.com/pressrelease/ | K1755: ayyappa-infra-projects-private-limited | Q1755: 2 | R1755: yg0r8xoabi2nh72hqsuefyv6 | S1755: Other | T1755: true | U1755: 2025-04-01T06:06:11.255Z | V1755: 2025-04-01T06:06:11.255Z | W1755: 2025-04-01T06:06:11.251Z
A1756: 6236 | B1756: otglbt5b1u0np85qwa4l5w00 | C1756: Prabodh Steel Private Limited | D1756: =VLOOKUP(C1756,'Scraped data '!A:A,1,0) -> Prabodh Steel Private Limited | F1756: true | G1756: 2022-10-07T09:52:35.000Z | H1756: 2026-02-02T06:21:53.002Z | I1756: 2026-02-02T06:21:52.826Z | J1756: https://www.infomerics.com/pressrelease/ | K1756: prabodh-steel-private-limited | Q1756: 2 | R1756: yg0r8xoabi2nh72hqsuefyv6 | S1756: Other | T1756: true | U1756: 2025-04-01T06:06:11.255Z | V1756: 2025-04-01T06:06:11.255Z | W1756: 2025-04-01T06:06:11.251Z
A1757: 6237 | B1757: j6znsvxegc6e9qhd4iqeuxai | C1757: Savi Global Fashion Private Limited (Erstwhile Savi Leathers) | D1757: =VLOOKUP(C1757,'Scraped data '!A:A,1,0) -> Savi Global Fashion Private Limited (Erstwhile Savi Leathers) | F1757: true | G1757: 2022-10-10T09:28:26.000Z | H1757: 2025-11-07T12:04:58.194Z | I1757: 2025-11-07T12:04:58.133Z | J1757: https://www.infomerics.com/pressrelease/ | K1757: savi-global-fashion-private-limited-erstwhile-savi-leathers | Q1757: 2 | R1757: yg0r8xoabi2nh72hqsuefyv6 | S1757: Other | T1757: true | U1757: 2025-04-01T06:06:11.255Z | V1757: 2025-04-01T06:06:11.255Z | W1757: 2025-04-01T06:06:11.251Z
A1758: 6238 | B1758: ha8segp719w1ggqjt8zucazp | C1758: Rexon Strips Limited | D1758: =VLOOKUP(C1758,'Scraped data '!A:A,1,0) -> Rexon Strips Limited | F1758: true | G1758: 2022-10-12T07:21:59.000Z | H1758: 2025-11-07T12:04:59.932Z | I1758: 2025-11-07T12:04:59.890Z | J1758: https://www.infomerics.com/pressrelease/ | K1758: rexon-strips-limited | Q1758: 2 | R1758: yg0r8xoabi2nh72hqsuefyv6 | S1758: Other | T1758: true | U1758: 2025-04-01T06:06:11.255Z | V1758: 2025-04-01T06:06:11.255Z | W1758: 2025-04-01T06:06:11.251Z
A1759: 6239 | B1759: xusb96pt987xepu4s5lax0wp | C1759: Metro Eco Green Resorts Limited | D1759: =VLOOKUP(C1759,'Scraped data '!A:A,1,0) -> Metro Eco Green Resorts Limited | F1759: true | G1759: 2022-10-13T10:22:44.000Z | H1759: 2025-11-07T12:05:02.250Z | I1759: 2025-11-07T12:05:02.184Z | J1759: https://www.infomerics.com/pressrelease/ | K1759: metro-eco-green-resorts-limited | Q1759: 2 | R1759: yg0r8xoabi2nh72hqsuefyv6 | S1759: Other | T1759: true | U1759: 2025-04-01T06:06:11.255Z | V1759: 2025-04-01T06:06:11.255Z | W1759: 2025-04-01T06:06:11.251Z
A1760: 6240 | B1760: olw0x487389ha1xmfwlgyd7o | C1760: Sharp Agricom Limited | D1760: =VLOOKUP(C1760,'Scraped data '!A:A,1,0) -> Sharp Agricom Limited | F1760: true | G1760: 2022-10-13T10:31:31.000Z | H1760: 2025-11-07T12:05:04.104Z | I1760: 2025-11-07T12:05:04.066Z | J1760: https://www.infomerics.com/pressrelease/ | K1760: sharp-agricom-limited | Q1760: 2 | R1760: yg0r8xoabi2nh72hqsuefyv6 | S1760: Other | T1760: true | U1760: 2025-04-01T06:06:11.255Z | V1760: 2025-04-01T06:06:11.255Z | W1760: 2025-04-01T06:06:11.251Z
A1761: 6241 | B1761: iezfrsabte4t5iih5b8m2u0v | C1761: Tirubala International Private Limited | D1761: =VLOOKUP(C1761,'Scraped data '!A:A,1,0) -> Tirubala International Private Limited | F1761: true | G1761: 2022-10-14T10:35:51.000Z | H1761: 2026-01-27T11:49:35.233Z | I1761: 2026-01-27T11:49:35.016Z | J1761: https://www.infomerics.com/pressrelease/ | K1761: tirubala-international-private-limited | Q1761: 2 | R1761: yg0r8xoabi2nh72hqsuefyv6 | S1761: Other | T1761: true | U1761: 2025-04-01T06:06:11.255Z | V1761: 2025-04-01T06:06:11.255Z | W1761: 2025-04-01T06:06:11.251Z
... A2383: 6863 | B2383: ntlel6n268wyxiaixaq8qdtd | C2383: Krivi Energy Private Limited (Erstwhile Krivi-Tex Private Limited) | D2383: =VLOOKUP(C2383,'Scraped data '!A:A,1,0) -> Krivi Energy Private Limited (Erstwhile Krivi-Tex Private Limited) | F2383: true | G2383: 2023-10-04T13:38:49.000Z | H2383: 2025-11-07T12:25:15.246Z | I2383: 2025-11-07T12:25:15.196Z | J2383: https://www.infomerics.com/pressrelease/ | K2383: krivi-energy-private-limited-erstwhile-krivitex-private-limited | Q2383: 2 | R2383: yg0r8xoabi2nh72hqsuefyv6 | S2383: Other | T2383: true | U2383: 2025-04-01T06:06:11.255Z | V2383: 2025-04-01T06:06:11.255Z | W2383: 2025-04-01T06:06:11.251Z
A2384: 6864 | B2384: yt9o6r4m0pwl41ht6tuplbm1 | C2384: Viyan Tex Industries LLP | D2384: =VLOOKUP(C2384,'Scraped data '!A:A,1,0) -> Viyan Tex Industries LLP | F2384: true | G2384: 2023-10-05T12:55:00.000Z | H2384: 2026-01-28T12:45:43.736Z | I2384: 2026-01-28T12:45:43.603Z | J2384: https://www.infomerics.com/pressrelease/ | K2384: viyan-tex-industries-llp
A2385: 6865 | B2385: t0ap11vu9zv0khfrbvb41d0b | C2385: G Rajam Chetty and Sons Jewellers LLP | D2385: =VLOOKUP(C2385,'Scraped data '!A:A,1,0) -> G Rajam Chetty and Sons Jewellers LLP | F2385: true | G2385: 2023-10-05T14:22:28.000Z | H2385: 2025-11-07T12:25:17.723Z | I2385: 2025-11-07T12:25:17.686Z | J2385: https://www.infomerics.com/pressrelease/ | K2385: g-rajam-chetty-and-sons-jewellers-llp | Q2385: 2 | R2385: yg0r8xoabi2nh72hqsuefyv6 | S2385: Other | T2385: true | U2385: 2025-04-01T06:06:11.255Z | V2385: 2025-04-01T06:06:11.255Z | W2385: 2025-04-01T06:06:11.251Z
A2386: 6866 | B2386: u2togieipbavimiuvsg5earc | C2386: Sitwanto Devi Mahila Kalyan Sansthan | D2386: =VLOOKUP(C2386,'Scraped data '!A:A,1,0) -> Sitwanto Devi Mahila Kalyan Sansthan | F2386: true | G2386: 2023-10-09T12:20:37.000Z | H2386: 2026-01-09T12:35:20.949Z | I2386: 2026-01-09T12:35:20.829Z | J2386: https://www.infomerics.com/pressrelease/ | K2386: sitwanto-devi-mahila-kalyan-sansthan | Q2386: 2 | R2386: yg0r8xoabi2nh72hqsuefyv6 | S2386: Other | T2386: true | U2386: 2025-04-01T06:06:11.255Z | V2386: 2025-04-01T06:06:11.255Z | W2386: 2025-04-01T06:06:11.251Z
A2387: 6867 | B2387: h0nc5cbrm1rleu147r7yybe0 | C2387: GSA Industries | D2387: =VLOOKUP(C2387,'Scraped data '!A:A,1,0) -> GSA Industries | F2387: true | G2387: 2023-10-10T11:28:48.000Z | H2387: 2026-01-13T12:13:26.210Z | I2387: 2026-01-13T12:13:26.044Z | J2387: https://www.infomerics.com/pressrelease/ | K2387: gsa-industries | Q2387: 2 | R2387: yg0r8xoabi2nh72hqsuefyv6 | S2387: Other | T2387: true | U2387: 2025-04-01T06:06:11.255Z | V2387: 2025-04-01T06:06:11.255Z | W2387: 2025-04-01T06:06:11.251Z
A2388: 6868 | B2388: i55mh7ne4jbmt3wf3eutr06q | C2388: Radharaman Cotspin Private Limited | D2388: =VLOOKUP(C2388,'Scraped data '!A:A,1,0) -> Radharaman Cotspin Private Limited | F2388: true | G2388: 2023-10-10T12:14:33.000Z | H2388: 2025-12-18T12:35:10.571Z | I2388: 2025-12-18T12:35:10.423Z | J2388: https://www.infomerics.com/pressrelease/ | K2388: radharaman-cotspin-private-limited | Q2388: 2 | R2388: yg0r8xoabi2nh72hqsuefyv6 | S2388: Other | T2388: true | U2388: 2025-04-01T06:06:11.255Z | V2388: 2025-04-01T06:06:11.255Z | W2388: 2025-04-01T06:06:11.251Z
A2389: 6869 | B2389: vv9eb2jd7da42pl1o6nbutvg | C2389: Shree Ramdoot Metloys Private Limited | D2389: =VLOOKUP(C2389,'Scraped data '!A:A,1,0) -> Shree Ramdoot Metloys Private Limited | F2389: true | G2389: 2023-10-11T05:26:23.000Z | H2389: 2026-01-09T12:08:05.784Z | I2389: 2026-01-09T12:08:05.655Z | J2389: https://www.infomerics.com/pressrelease/ | K2389: shree-ramdoot-metloys-private-limited | Q2389: 2 | R2389: yg0r8xoabi2nh72hqsuefyv6 | S2389: Other | T2389: true | U2389: 2025-04-01T06:06:11.255Z | V2389: 2025-04-01T06:06:11.255Z | W2389: 2025-04-01T06:06:11.251Z
A2390: 6870 | B2390: qch86jf0rf81btgibntx42d9 | C2390: Believers Eastern Church | D2390: =VLOOKUP(C2390,'Scraped data '!A:A,1,0) -> Believers Eastern Church | F2390: true | G2390: 2023-10-11T06:31:22.000Z | H2390: 2025-11-07T12:25:24.121Z | I2390: 2025-11-07T12:25:24.086Z | J2390: https://www.infomerics.com/pressrelease/ | K2390: believers-eastern-church | Q2390: 2 | R2390: yg0r8xoabi2nh72hqsuefyv6 | S2390: Other | T2390: true | U2390: 2025-04-01T06:06:11.255Z | V2390: 2025-04-01T06:06:11.255Z | W2390: 2025-04-01T06:06:11.251Z
A2391: 6871 | B2391: rasxvxcx7jfh5yp65nes9h99 | C2391: Taj Granites Private Limited | D2391: =VLOOKUP(C2391,'Scraped data '!A:A,1,0) -> Taj Granites Private Limited | F2391: true | G2391: 2023-10-11T06:36:19.000Z | H2391: 2025-11-07T12:25:25.394Z | I2391: 2025-11-07T12:25:25.365Z | J2391: https://www.infomerics.com/pressrelease/ | K2391: taj-granites-private-limited | Q2391: 2 | R2391: yg0r8xoabi2nh72hqsuefyv6 | S2391: Other | T2391: true | U2391: 2025-04-01T06:06:11.255Z | V2391: 2025-04-01T06:06:11.255Z | W2391: 2025-04-01T06:06:11.251Z
A2392: 6872 | B2392: ens837phzdqqtm8cjwysy6g1 | C2392: Spica Projects And Infrastructure Private Limited | D2392: =VLOOKUP(C2392,'Scraped data '!A:A,1,0) -> Spica Projects And Infrastructure Private Limited | F2392: true | G2392: 2023-10-11T07:41:15.000Z | H2392: 2026-01-23T13:29:03.072Z | I2392: 2026-01-23T13:29:02.953Z | J2392: https://www.infomerics.com/pressrelease/ | K2392: spica-projects-and-infrastructure-private-limited | Q2392: 2 | R2392: yg0r8xoabi2nh72hqsuefyv6 | S2392: Other | T2392: true | U2392: 2025-04-01T06:06:11.255Z | V2392: 2025-04-01T06:06:11.255Z | W2392: 2025-04-01T06:06:11.251Z
A2393: 6873 | B2393: cxo9pnsk6aw7f27hxr94ntwb | C2393: Panyam Cements and Minerals Industries Limited | D2393: =VLOOKUP(C2393,'Scraped data '!A:A,1,0) -> Panyam Cements and Minerals Industries Limited | F2393: true | G2393: 2023-10-11T11:25:53.000Z | H2393: 2026-01-06T13:01:45.969Z | I2393: 2026-01-06T13:01:45.782Z | J2393: https://www.infomerics.com/pressrelease/ | K2393: panyam-cements-and-minerals-industries-limited | Q2393: 2 | R2393: yg0r8xoabi2nh72hqsuefyv6 | S2393: Other | T2393: true | U2393: 2025-04-01T06:06:11.255Z | V2393: 2025-04-01T06:06:11.255Z | W2393: 2025-04-01T06:06:11.251Z
A2394: 6874 | B2394: e8ap0h1uwigkcpykufvwhg58 | C2394: R. S. Infra Transmission Limited | D2394: =VLOOKUP(C2394,'Scraped data '!A:A,1,0) -> R. S. Infra Transmission Limited | F2394: true | G2394: 2023-10-11T12:42:25.000Z | H2394: 2025-11-07T12:25:30.980Z | I2394: 2025-11-07T12:25:30.899Z | J2394: https://www.infomerics.com/pressrelease/ | K2394: r-s-infra-transmission-limited | Q2394: 2 | R2394: yg0r8xoabi2nh72hqsuefyv6 | S2394: Other | T2394: true | U2394: 2025-04-01T06:06:11.255Z | V2394: 2025-04-01T06:06:11.255Z | W2394: 2025-04-01T06:06:11.251Z
A2395: 6875 | B2395: b8ffuwb0twbrftk5b0qodtkx | C2395: R K Lighting Private Limited | D2395: =VLOOKUP(C2395,'Scraped data '!A:A,1,0) -> R K Lighting Private Limited | F2395: true | G2395: 2023-10-12T05:46:37.000Z | H2395: 2025-11-07T12:25:33.607Z | I2395: 2025-11-07T12:25:33.545Z | J2395: https://www.infomerics.com/pressrelease/ | K2395: r-k-lighting-private-limited | Q2395: 2 | R2395: yg0r8xoabi2nh72hqsuefyv6 | S2395: Other | T2395: true | U2395: 2025-04-01T06:06:11.255Z | V2395: 2025-04-01T06:06:11.255Z | W2395: 2025-04-01T06:06:11.251Z
A2396: 6876 | B2396: l0nmuu7pkenrxtk7xrz0g9yi | C2396: Nova Textiles Private Limited | D2396: =VLOOKUP(C2396,'Scraped data '!A:A,1,0) -> Nova Textiles Private Limited | F2396: true | G2396: 2023-10-12T05:58:29.000Z | H2396: 2025-11-07T12:25:35.183Z | I2396: 2025-11-07T12:25:35.145Z | J2396: https://www.infomerics.com/pressrelease/ | K2396: nova-textiles-private-limited | Q2396: 2 | R2396: yg0r8xoabi2nh72hqsuefyv6 | S2396: Other | T2396: true | U2396: 2025-04-01T06:06:11.255Z | V2396: 2025-04-01T06:06:11.255Z | W2396: 2025-04-01T06:06:11.251Z
... A2893: 7374 | B2893: uc85ljen61tijaxums0o6a0k | C2893: Pongalur Pioneer Textiles Private Limited | D2893: =VLOOKUP(C2893,'Scraped data '!A:A,1,0) -> Pongalur Pioneer Textiles Private Limited | F2893: true | G2893: 2024-07-24T12:24:20.000Z | H2893: 2025-11-07T12:37:40.485Z | I2893: 2025-11-07T12:37:40.454Z | J2893: https://www.infomerics.com/pressrelease/ | K2893: pongalur-pioneer-textiles-private-limited | Q2893: 2 | R2893: yg0r8xoabi2nh72hqsuefyv6 | S2893: Other | T2893: true | U2893: 2025-04-01T06:06:11.255Z | V2893: 2025-04-01T06:06:11.255Z | W2893: 2025-04-01T06:06:11.251Z
A2894: 7375 | B2894: oeqmlayxjl7h4fcsrat04jlm | C2894: Micropark Logistics Private Limited | D2894: =VLOOKUP(C2894,'Scraped data '!A:A,1,0) -> Micropark Logistics Private Limited | F2894: true | G2894: 2024-07-25T05:15:58.000Z | H2894: 2026-02-03T05:24:56.066Z | I2894: 2026-02-03T05:24:55.902Z | J2894: https://www.infomerics.com/pressrelease/ | K2894: micropark-logistics-private-limited
A2895: 7376 | B2895: g154w1clhqnwp416w0cywicb | C2895: Imperial Distillers and Vintners Private Limited | D2895: =VLOOKUP(C2895,'Scraped data '!A:A,1,0) -> Imperial Distillers and Vintners Private Limited | F2895: true | G2895: 2024-07-25T10:58:35.000Z | H2895: 2025-11-19T19:20:01.889Z | I2895: 2025-11-19T19:20:01.847Z | J2895: https://www.infomerics.com/pressrelease/ | K2895: imperial-distillers-and-vintners-private-limited | Q2895: 2 | R2895: yg0r8xoabi2nh72hqsuefyv6 | S2895: Other | T2895: true | U2895: 2025-04-01T06:06:11.255Z | V2895: 2025-04-01T06:06:11.255Z | W2895: 2025-04-01T06:06:11.251Z
A2896: 7377 | B2896: x1tbir3hf08tbzuppfy0kzi8 | C2896: Savani Corporation | D2896: =VLOOKUP(C2896,'Scraped data '!A:A,1,0) -> Savani Corporation | F2896: true | G2896: 2024-07-26T11:20:51.000Z | H2896: 2025-11-07T12:37:44.172Z | I2896: 2025-11-07T12:37:44.145Z | J2896: https://www.infomerics.com/pressrelease/ | K2896: savani-corporation | Q2896: 2 | R2896: yg0r8xoabi2nh72hqsuefyv6 | S2896: Other | T2896: true | U2896: 2025-04-01T06:06:11.255Z | V2896: 2025-04-01T06:06:11.255Z | W2896: 2025-04-01T06:06:11.251Z
A2897: 7378 | B2897: ybiiw7xf37f89k3qbeasxjvq | C2897: Reilly Homes Realty Private Limited | D2897: =VLOOKUP(C2897,'Scraped data '!A:A,1,0) -> Reilly Homes Realty Private Limited | F2897: true | G2897: 2024-07-26T12:45:26.000Z | H2897: 2025-11-07T12:37:45.403Z | I2897: 2025-11-07T12:37:45.369Z | J2897: https://www.infomerics.com/pressrelease/ | K2897: reilly-homes-realty-private-limited | Q2897: 2 | R2897: yg0r8xoabi2nh72hqsuefyv6 | S2897: Other | T2897: true | U2897: 2025-04-01T06:06:11.255Z | V2897: 2025-04-01T06:06:11.255Z | W2897: 2025-04-01T06:06:11.251Z
A2898: 7379 | B2898: ieno7jscqerpt0hm03z161ne | C2898: Devaki Motors LLP | D2898: =VLOOKUP(C2898,'Scraped data '!A:A,1,0) -> Devaki Motors LLP | F2898: true | G2898: 2024-07-30T05:44:20.000Z | H2898: 2026-02-03T08:07:00.116Z | I2898: 2026-02-03T08:06:59.942Z | J2898: https://www.infomerics.com/pressrelease/ | K2898: devaki-motors-llp | Q2898: 2 | R2898: yg0r8xoabi2nh72hqsuefyv6 | S2898: Other | T2898: true | U2898: 2025-04-01T06:06:11.255Z | V2898: 2025-04-01T06:06:11.255Z | W2898: 2025-04-01T06:06:11.251Z
A2899: 7380 | B2899: e3ovzmt4atzsmupy9gsv5wh5 | C2899: Bharatiyam Beverages Private Limited | D2899: =VLOOKUP(C2899,'Scraped data '!A:A,1,0) -> Bharatiyam Beverages Private Limited | F2899: true | G2899: 2024-07-30T06:47:17.000Z | H2899: 2025-11-07T12:37:48.037Z | I2899: 2025-11-07T12:37:48.011Z | J2899: https://www.infomerics.com/pressrelease/ | K2899: bharatiyam-beverages-private-limited | Q2899: 2 | R2899: yg0r8xoabi2nh72hqsuefyv6 | S2899: Other | T2899: true | U2899: 2025-04-01T06:06:11.255Z | V2899: 2025-04-01T06:06:11.255Z | W2899: 2025-04-01T06:06:11.251Z
A2900: 7381 | B2900: mo91zxxmrctiqsose2dnaf5e | C2900: Ornate Mercantile Private Limited | D2900: =VLOOKUP(C2900,'Scraped data '!A:A,1,0) -> Ornate Mercantile Private Limited | F2900: true | G2900: 2024-07-30T07:18:37.000Z | H2900: 2025-11-07T12:37:49.340Z | I2900: 2025-11-07T12:37:49.310Z | J2900: https://www.infomerics.com/pressrelease/ | K2900: ornate-mercantile-private-limited | Q2900: 2 | R2900: yg0r8xoabi2nh72hqsuefyv6 | S2900: Other | T2900: true | U2900: 2025-04-01T06:06:11.255Z | V2900: 2025-04-01T06:06:11.255Z | W2900: 2025-04-01T06:06:11.251Z
A2901: 7382 | B2901: petx0g707n5iybo82rxd1xzg | C2901: Al Ammar Frozen Foods Exports Private Limited | D2901: =VLOOKUP(C2901,'Scraped data '!A:A,1,0) -> Al Ammar Frozen Foods Exports Private Limited | F2901: true | G2901: 2024-07-30T09:26:53.000Z | H2901: 2025-11-07T12:37:50.590Z | I2901: 2025-11-07T12:37:50.564Z | J2901: https://www.infomerics.com/pressrelease/ | K2901: al-ammar-frozen-foods-exports-private-limited | Q2901: 2 | R2901: yg0r8xoabi2nh72hqsuefyv6 | S2901: Other | T2901: true | U2901: 2025-04-01T06:06:11.255Z | V2901: 2025-04-01T06:06:11.255Z | W2901: 2025-04-01T06:06:11.251Z
A2902: 7383 | B2902: oqawdo44hh19nv1wotcegejj | C2902: Kanjiravelil Traders Private Limited | D2902: =VLOOKUP(C2902,'Scraped data '!A:A,1,0) -> Kanjiravelil Traders Private Limited | F2902: true | G2902: 2024-07-30T10:20:19.000Z | H2902: 2025-11-07T12:37:51.593Z | I2902: 2025-11-07T12:37:51.564Z | J2902: https://www.infomerics.com/pressrelease/ | K2902: kanjiravelil-traders-private-limited | Q2902: 2 | R2902: yg0r8xoabi2nh72hqsuefyv6 | S2902: Other | T2902: true | U2902: 2025-04-01T06:06:11.255Z | V2902: 2025-04-01T06:06:11.255Z | W2902: 2025-04-01T06:06:11.251Z
A2903: 7384 | B2903: u14bk48dj1jidxrtcxphszhq | C2903: Mohan Spintex India Limited | D2903: =VLOOKUP(C2903,'Scraped data '!A:A,1,0) -> Mohan Spintex India Limited | F2903: true | G2903: 2024-07-30T11:36:29.000Z | H2903: 2025-11-07T12:37:52.872Z | I2903: 2025-11-07T12:37:52.844Z | J2903: https://www.infomerics.com/pressrelease/ | K2903: mohan-spintex-india-limited | Q2903: 2 | R2903: yg0r8xoabi2nh72hqsuefyv6 | S2903: Other | T2903: true | U2903: 2025-04-01T06:06:11.255Z | V2903: 2025-04-01T06:06:11.255Z | W2903: 2025-04-01T06:06:11.251Z
A2904: 7385 | B2904: k8zvjw7w6uqtkhvdsn8mcn9a | C2904: Sirsaliya Vinod Green Energy Private Limited | D2904: =VLOOKUP(C2904,'Scraped data '!A:A,1,0) -> Sirsaliya Vinod Green Energy Private Limited | F2904: true | G2904: 2024-07-31T12:56:33.000Z | H2904: 2025-11-26T06:20:35.561Z | I2904: 2025-11-26T06:20:35.421Z | J2904: https://www.infomerics.com/pressrelease/ | K2904: sirsaliya-vinod-green-energy-private-limited | Q2904: 2 | R2904: yg0r8xoabi2nh72hqsuefyv6 | S2904: Other | T2904: true | U2904: 2025-04-01T06:06:11.255Z | V2904: 2025-04-01T06:06:11.255Z | W2904: 2025-04-01T06:06:11.251Z
A2905: 7386 | B2905: zbd8cxj3qrkjfw8vhx5in0at | C2905: PSAA Constructions Private Limited | D2905: =VLOOKUP(C2905,'Scraped data '!A:A,1,0) -> PSAA Constructions Private Limited | F2905: true | G2905: 2024-08-01T09:34:35.000Z | H2905: 2025-11-20T04:58:28.385Z | I2905: 2025-11-20T04:58:28.322Z | J2905: https://www.infomerics.com/pressrelease/ | K2905: psaa-constructions-private-limited | Q2905: 2 | R2905: yg0r8xoabi2nh72hqsuefyv6 | S2905: Other | T2905: true | U2905: 2025-04-01T06:06:11.255Z | V2905: 2025-04-01T06:06:11.255Z | W2905: 2025-04-01T06:06:11.251Z
A2906: 7387 | B2906: fv5rlg3huh1rimhzs4cxw89w | C2906: Esteemed Developers & Builders Private Limited | D2906: =VLOOKUP(C2906,'Scraped data '!A:A,1,0) -> Esteemed Developers & Builders Private Limited | F2906: true | G2906: 2024-08-01T10:35:58.000Z | H2906: 2025-11-07T12:37:56.240Z | I2906: 2025-11-07T12:37:56.210Z | J2906: https://www.infomerics.com/pressrelease/ | K2906: esteemed-developers--builders-private-limited | Q2906: 2 | R2906: yg0r8xoabi2nh72hqsuefyv6 | S2906: Other | T2906: true | U2906: 2025-04-01T06:06:11.255Z | V2906: 2025-04-01T06:06:11.255Z | W2906: 2025-04-01T06:06:11.251Z
... A3057: 7538 | B3057: qhmv2gsga9m7vg1owfe2fj83 | C3057: Skill Tree Consulting Limited | D3057: =VLOOKUP(C3057,'Scraped data '!A:A,1,0) -> Skill Tree Consulting Limited | F3057: true | G3057: 2024-10-18T12:36:20.000Z | H3057: 2025-12-30T10:45:54.320Z | I3057: 2025-12-30T10:45:54.136Z | J3057: https://www.infomerics.com/pressrelease/ | K3057: skill-tree-consulting-limited | Q3057: 2 | R3057: yg0r8xoabi2nh72hqsuefyv6 | S3057: Other | T3057: true | U3057: 2025-04-01T06:06:11.255Z | V3057: 2025-04-01T06:06:11.255Z | W3057: 2025-04-01T06:06:11.251Z
A3058: 7539 | B3058: m850xo3wt7ef28vrurgu43lf | C3058: Markolines Infra Limited | D3058: =VLOOKUP(C3058,'Scraped data '!A:A,1,0) -> Markolines Infra Limited | F3058: true | G3058: 2024-10-18T12:42:33.000Z | H3058: 2025-11-19T15:06:00.993Z | I3058: 2025-11-19T15:06:00.873Z | J3058: https://www.infomerics.com/pressrelease/ | K3058: markolines-infra-limited
...
